Workbook
Name Slicer_City1: #N/A
Name Slicer_Loan_Type1: #N/A
Name Slicer_years: #N/A

Sheet introduction

Sheet data
A1: HDFC BANK LOAN DATA 2024 TO 2026
A2: Loan_ID | B2: customer_name | C2: Age | D2: Gender | E2: City | F2: Loan_Type | G2: years | H2: months | I2: Application_Date | J2: EMI_payment_date | K2: Annual_Income | L2: monthly_income | M2: Loan_Amount | N2: month_paid | O2: total_amount_paid | P2: Interest_Rate | Q2: monthly_EMI | R2: Loan_Term_Months | S2: Credit_Score | T2: Repayment_Status | U2: good vs bad loan | V2: Default_Risk | W2: DTI | X2: Profit
A3: L0095 | B3: Meera Nair | C3: 55 | D3: Male | E3: Pune | F3: Education | G3: =YEAR(Table1[[#This Row],[Application_Date]]) -> 2024 | H3: =TEXT(Table1[[#This Row],[EMI_payment_date]],"mmmm") -> May | I3: 45383 | J3: =EDATE(Table1[[#This Row],[Application_Date]],1) -> 45413 | K3: 1728000 | L3: =Table1[[#This Row],[Annual_Income]]/12 -> 144000 | M3: 1928000 | N3: =DATEDIF(Table1[[#This Row],[EMI_payment_date]],TODAY(),"m") -> 26 | O3: =Table1[[#This Row],[month_paid]]*Table1[[#This Row],[monthly_EMI]] -> 1123200 | P3: 7.51 | Q3: =Table1[[#This Row],[monthly_income]]*30% -> 43200 | R3: =ROUNDUP(NPER(P3/100/12,-Q3,Table1[[#This Row],[Loan_Amount]]),0) -> 53 | S3: 688 | T3: Late | U3: =IF(Table1[[#This Row],[Repayment_Status]]="late","bad loan","good loan") -> bad loan | V3: =IF(Table1[[#This Row],[Repayment_Status]]="late","high","low") -> high | W3: =(Table1[[#This Row],[monthly_EMI]]/Table1[[#This Row],[monthly_income]])*100 -> 30 | X3: 31178.55
A4: L0087 | B4: Neha Yadav | C4: 26 | D4: Female | E4: Delhi | F4: Personal | G4: =YEAR(Table1[[#This Row],[Application_Date]]) -> 2024 | H4: =TEXT(Table1[[#This Row],[EMI_payment_date]],"mmmm") -> May | I4: 45384 | J4: =EDATE(Table1[[#This Row],[Application_Date]],1) -> 45414 | K4: 1632000 | L4: =Table1[[#This Row],[Annual_Income]]/12 -> 136000 | M4: 1832000 | N4: =DATEDIF(Table1[[#This Row],[EMI_payment_date]],TODAY(),"m") -> 26 | O4: =Table1[[#This Row],[month_paid]]*Table1[[#This Row],[monthly_EMI]] -> 1060800 | P4: 8.51 | Q4: =Table1[[#This Row],[monthly_income]]*30% -> 40800 | R4: =ROUNDUP(NPER(P4/100/12,-Q4,Table1[[#This Row],[Loan_Amount]]),0) -> 55 | S4: 750 | T4: Completed | U4: =IF(Table1[[#This Row],[Repayment_Status]]="late","bad loan","good loan") -> good loan | V4: =IF(Table1[[#This Row],[Repayment_Status]]="late","high","low") -> low | W4: =(Table1[[#This Row],[monthly_EMI]]/Table1[[#This Row],[monthly_income]])*100 -> 30 | X4: 23469.34
A5: L0549 | B5: Rohan Nair | C5: 29 | D5: Female | E5: Chennai | F5: Personal | G5: =YEAR(Table1[[#This Row],[Application_Date]]) -> 2024 | H5: =TEXT(Table1[[#This Row],[EMI_payment_date]],"mmmm") -> May | I5: 45385 | J5: =EDATE(Table1[[#This Row],[Application_Date]],1) -> 45415 | K5: 7176000 | L5: =Table1[[#This Row],[Annual_Income]]/12 -> 598000 | M5: 7376000 | N5: =DATEDIF(Table1[[#This Row],[EMI_payment_date]],TODAY(),"m") -> 26 | O5: =Table1[[#This Row],[month_paid]]*Table1[[#This Row],[monthly_EMI]] -> 4664400 | P5: 5.21 | Q5: =Table1[[#This Row],[monthly_income]]*30% -> 179400 | R5: =ROUNDUP(NPER(P5/100/12,-Q5,Table1[[#This Row],[Loan_Amount]]),0) -> 46 | S5: 707 | T5: Completed | U5: =IF(Table1[[#This Row],[Repayment_Status]]="late","bad loan","good loan") -> good loan | V5: =IF(Table1[[#This Row],[Repayment_Status]]="late","high","low") -> low | W5: =(Table1[[#This Row],[monthly_EMI]]/Table1[[#This Row],[monthly_income]])*100 -> 30 | X5: 10514.14
A6: L0442 | B6: Rahul Sharma | C6: 48 | D6: Female | E6: Delhi | F6: Home | G6: =YEAR(Table1[[#This Row],[Application_Date]]) -> 2024 | H6: =TEXT(Table1[[#This Row],[EMI_payment_date]],"mmmm") -> May | I6: 45386 | J6: =EDATE(Table1[[#This Row],[Application_Date]],1) -> 45416 | K6: 5892000 | L6: =Table1[[#This Row],[Annual_Income]]/12 -> 491000 | M6: 6092000 | N6: =DATEDIF(Table1[[#This Row],[EMI_payment_date]],TODAY(),"m") -> 26 | O6: =Table1[[#This Row],[month_paid]]*Table1[[#This Row],[monthly_EMI]] -> 3829800 | P6: 9.95 | Q6: =Table1[[#This Row],[monthly_income]]*30% -> 147300 | R6: =ROUNDUP(NPER(P6/100/12,-Q6,Table1[[#This Row],[Loan_Amount]]),0) -> 51 | S6: 848 | T6: Late | U6: =IF(Table1[[#This Row],[Repayment_Status]]="late","bad loan","good loan") -> bad loan | V6: =IF(Table1[[#This Row],[Repayment_Status]]="late","high","low") -> high | W6: =(Table1[[#This Row],[monthly_EMI]]/Table1[[#This Row],[monthly_income]])*100 -> 30 | X6: 26808.54
A7: L0409 | B7: Rahul Mehta | C7: 50 | D7: Male | E7: Chennai | F7: Home | G7: =YEAR(Table1[[#This Row],[Application_Date]]) -> 2024 | H7: =TEXT(Table1[[#This Row],[EMI_payment_date]],"mmmm") -> May | I7: 45387 | J7: =EDATE(Table1[[#This Row],[Application_Date]],1) -> 45417 | K7: 5496000 | L7: =Table1[[#This Row],[Annual_Income]]/12 -> 458000 | M7: 5696000 | N7: =DATEDIF(Table1[[#This Row],[EMI_payment_date]],TODAY(),"m") -> 26 | O7: =Table1[[#This Row],[month_paid]]*Table1[[#This Row],[monthly_EMI]] -> 3572400 | P7: 6.55 | Q7: =Table1[[#This Row],[monthly_income]]*30% -> 137400 | R7: =ROUNDUP(NPER(P7/100/12,-Q7,Table1[[#This Row],[Loan_Amount]]),0) -> 48 | S7: 804 | T7: Completed | U7: =IF(Table1[[#This Row],[Repayment_Status]]="late","bad loan","good loan") -> good loan | V7: =IF(Table1[[#This Row],[Repayment_Status]]="late","high","low") -> low | W7: =(Table1[[#This Row],[monthly_EMI]]/Table1[[#This Row],[monthly_income]])*100 -> 30 | X7: 25945.11
A8: L0457 | B8: Karan Mehta | C8: 36 | D8: Female | E8: Pune | F8: Personal | G8: =YEAR(Table1[[#This Row],[Application_Date]]) -> 2024 | H8: =TEXT(Table1[[#This Row],[EMI_payment_date]],"mmmm") -> May | I8: 45388 | J8: =EDATE(Table1[[#This Row],[Application_Date]],1) -> 45418 | K8: 6072000 | L8: =Table1[[#This Row],[Annual_Income]]/12 -> 506000 | M8: 6272000 | N8: =DATEDIF(Table1[[#This Row],[EMI_payment_date]],TODAY(),"m") -> 26 | O8: =Table1[[#This Row],[month_paid]]*Table1[[#This Row],[monthly_EMI]] -> 3946800 | P8: 9.26 | Q8: =Table1[[#This Row],[monthly_income]]*30% -> 151800 | R8: =ROUNDUP(NPER(P8/100/12,-Q8,Table1[[#This Row],[Loan_Amount]]),0) -> 50 | S8: 812 | T8: Completed | U8: =IF(Table1[[#This Row],[Repayment_Status]]="late","bad loan","good loan") -> good loan | V8: =IF(Table1[[#This Row],[Repayment_Status]]="late","high","low") -> low | W8: =(Table1[[#This Row],[monthly_EMI]]/Table1[[#This Row],[monthly_income]])*100 -> 30 | X8: 22853.64
A9: L0041 | B9: Kavya Yadav | C9: 23 | D9: Male | E9: Delhi | F9: Business | G9: =YEAR(Table1[[#This Row],[Application_Date]]) -> 2024 | H9: =TEXT(Table1[[#This Row],[EMI_payment_date]],"mmmm") -> May | I9: 45389 | J9: =EDATE(Table1[[#This Row],[Application_Date]],1) -> 45419 | K9: 1080000 | L9: =Table1[[#This Row],[Annual_Income]]/12 -> 90000 | M9: 1280000 | N9: =DATEDIF(Table1[[#This Row],[EMI_payment_date]],TODAY(),"m") -> 26 | O9: =Table1[[#This Row],[month_paid]]*Table1[[#This Row],[monthly_EMI]] -> 702000 | P9: 5.39 | Q9: =Table1[[#This Row],[monthly_income]]*30% -> 27000 | R9: =ROUNDUP(NPER(P9/100/12,-Q9,Table1[[#This Row],[Loan_Amount]]),0) -> 54 | S9: 831 | T9: Late | U9: =IF(Table1[[#This Row],[Repayment_Status]]="late","bad loan","good loan") -> bad loan | V9: =IF(Table1[[#This Row],[Repayment_Status]]="late","high","low") -> high | W9: =(Table1[[#This Row],[monthly_EMI]]/Table1[[#This Row],[monthly_income]])*100 -> 30 | X9: 12860.1
A10: L0545 | B10: Priya Patel | C10: 27 | D10: Male | E10: Bengaluru | F10: Home | G10: =YEAR(Table1[[#This Row],[Application_Date]]) -> 2024 | H10: =TEXT(Table1[[#This Row],[EMI_payment_date]],"mmmm") -> May | I10: 45390 | J10: =EDATE(Table1[[#This Row],[Application_Date]],1) -> 45420 | K10: 7128000 | L10: =Table1[[#This Row],[Annual_Income]]/12 -> 594000 | M10: 7328000 | N10: =DATEDIF(Table1[[#This Row],[EMI_payment_date]],TODAY(),"m") -> 26 | O10: =Table1[[#This Row],[month_paid]]*Table1[[#This Row],[monthly_EMI]] -> 4633200 | P10: 8.64 | Q10: =Table1[[#This Row],[monthly_income]]*30% -> 178200 | R10: =ROUNDUP(NPER(P10/100/12,-Q10,Table1[[#This Row],[Loan_Amount]]),0) -> 49 | S10: 732 | T10: Late | U10: =IF(Table1[[#This Row],[Repayment_Status]]="late","bad loan","good loan") -> bad loan | V10: =IF(Table1[[#This Row],[Repayment_Status]]="late","high","low") -> high | W10: =(Table1[[#This Row],[monthly_EMI]]/Table1[[#This Row],[monthly_income]])*100 -> 30 | X10: 30989.8
A11: L0346 | B11: Ananya Mehta | C11: 30 | D11: Female | E11: Hyderabad | F11: Car | G11: =YEAR(Table1[[#This Row],[Application_Date]]) -> 2024 | H11: =TEXT(Table1[[#This Row],[EMI_payment_date]],"mmmm") -> May | I11: 45391 | J11: =EDATE(Table1[[#This Row],[Application_Date]],1) -> 45421 | K11: 4740000 | L11: =Table1[[#This Row],[Annual_Income]]/12 -> 395000 | M11: 4940000 | N11: =DATEDIF(Table1[[#This Row],[EMI_payment_date]],TODAY(),"m") -> 26 | O11: =Table1[[#This Row],[month_paid]]*Table1[[#This Row],[monthly_EMI]] -> 3081000 | P11: 7.16 | Q11: =Table1[[#This Row],[monthly_income]]*30% -> 118500 | R11: =ROUNDUP(NPER(P11/100/12,-Q11,Table1[[#This Row],[Loan_Amount]]),0) -> 49 | S11: 746 | T11: Completed | U11: =IF(Table1[[#This Row],[Repayment_Status]]="late","bad loan","good loan") -> good loan | V11: =IF(Table1[[#This Row],[Repayment_Status]]="late","high","low") -> low | W11: =(Table1[[#This Row],[monthly_EMI]]/Table1[[#This Row],[monthly_income]])*100 -> 30 | X11: 26278.03
A12: L0534 | B12: Kavya Verma | C12: 37 | D12: Male | E12: Hyderabad | F12: Business | G12: =YEAR(Table1[[#This Row],[Application_Date]]) -> 2024 | H12: =TEXT(Table1[[#This Row],[EMI_payment_date]],"mmmm") -> May | I12: 45392 | J12: =EDATE(Table1[[#This Row],[Application_Date]],1) -> 45422 | K12: 6996000 | L12: =Table1[[#This Row],[Annual_Income]]/12 -> 583000 | M12: 7196000 | N12: =DATEDIF(Table1[[#This Row],[EMI_payment_date]],TODAY(),"m") -> 26 | O12: =Table1[[#This Row],[month_paid]]*Table1[[#This Row],[monthly_EMI]] -> 4547400 | P12: 9.63 | Q12: =Table1[[#This Row],[monthly_income]]*30% -> 174900 | R12: =ROUNDUP(NPER(P12/100/12,-Q12,Table1[[#This Row],[Loan_Amount]]),0) -> 51 | S12: 753 | T12: Completed | U12: =IF(Table1[[#This Row],[Repayment_Status]]="late","bad loan","good loan") -> good loan | V12: =IF(Table1[[#This Row],[Repayment_Status]]="late","high","low") -> low | W12: =(Table1[[#This Row],[monthly_EMI]]/Table1[[#This Row],[monthly_income]])*100 -> 30 | X12: 23757.02
A13: L0116 | B13: Ritika Nair | C13: 29 | D13: Female | E13: Mumbai | F13: Home | G13: =YEAR(Table1[[#This Row],[Application_Date]]) -> 2024 | H13: =TEXT(Table1[[#This Row],[EMI_payment_date]],"mmmm") -> May | I13: 45393 | J13: =EDATE(Table1[[#This Row],[Application_Date]],1) -> 45423 | K13: 1980000 | L13: =Table1[[#This Row],[Annual_Income]]/12 -> 165000 | M13: 2180000 | N13: =DATEDIF(Table1[[#This Row],[EMI_payment_date]],TODAY(),"m") -> 26 | O13: =Table1[[#This Row],[month_paid]]*Table1[[#This Row],[monthly_EMI]] -> 1287000 | P13: 7.42 | Q13: =Table1[[#This Row],[monthly_income]]*30% -> 49500 | R13: =ROUNDUP(NPER(P13/100/12,-Q13,Table1[[#This Row],[Loan_Amount]]),0) -> 52 | S13: 838 | T13: Late | U13: =IF(Table1[[#This Row],[Repayment_Status]]="late","bad loan","good loan") -> bad loan | V13: =IF(Table1[[#This Row],[Repayment_Status]]="late","high","low") -> high | W13: =(Table1[[#This Row],[monthly_EMI]]/Table1[[#This Row],[monthly_income]])*100 -> 30 | X13: 22554.62
A14: L0321 | B14: Aisha Gupta | C14: 58 | D14: Female | E14: Mumbai | F14: Personal | G14: =YEAR(Table1[[#This Row],[Application_Date]]) -> 2024 | H14: =TEXT(Table1[[#This Row],[EMI_payment_date]],"mmmm") -> May | I14: 45394 | J14: =EDATE(Table1[[#This Row],[Application_Date]],1) -> 45424 | K14: 4440000 | L14: =Table1[[#This Row],[Annual_Income]]/12 -> 370000 | M14: 4640000 | N14: =DATEDIF(Table1[[#This Row],[EMI_payment_date]],TODAY(),"m") -> 26 | O14: =Table1[[#This Row],[month_paid]]*Table1[[#This Row],[monthly_EMI]] -> 2886000 | P14: 7.88 | Q14: =Table1[[#This Row],[monthly_income]]*30% -> 111000 | R14: =ROUNDUP(NPER(P14/100/12,-Q14,Table1[[#This Row],[Loan_Amount]]),0) -> 50 | S14: 778 | T14: Completed | U14: =IF(Table1[[#This Row],[Repayment_Status]]="late","bad loan","good loan") -> good loan | V14: =IF(Table1[[#This Row],[Repayment_Status]]="late","high","low") -> low | W14: =(Table1[[#This Row],[monthly_EMI]]/Table1[[#This Row],[monthly_income]])*100 -> 30 | X14: 18855.34
... A216: L0648 | B216: Rohan Sharma | C216: 53 | D216: Male | E216: Bengaluru | F216: Business | G216: =YEAR(Table1[[#This Row],[Application_Date]]) -> 2024 | H216: =TEXT(Table1[[#This Row],[EMI_payment_date]],"mmmm") -> November | I216: 45596 | J216: =EDATE(Table1[[#This Row],[Application_Date]],1) -> 45626 | K216: 8364000 | L216: =Table1[[#This Row],[Annual_Income]]/12 -> 697000 | M216: 8564000 | N216: =DATEDIF(Table1[[#This Row],[EMI_payment_date]],TODAY(),"m") -> 20 | O216: =Table1[[#This Row],[month_paid]]*Table1[[#This Row],[monthly_EMI]] -> 4182000 | P216: 6.94 | Q216: =Table1[[#This Row],[monthly_income]]*30% -> 209100 | R216: =ROUNDUP(NPER(P216/100/12,-Q216,Table1[[#This Row],[Loan_Amount]]),0) -> 47 | S216: 661 | T216: Late | U216: =IF(Table1[[#This Row],[Repayment_Status]]="late","bad loan","good loan") -> bad loan | V216: =IF(Table1[[#This Row],[Repayment_Status]]="late","high","low") -> high | W216: =(Table1[[#This Row],[monthly_EMI]]/Table1[[#This Row],[monthly_income]])*100 -> 30 | X216: 5968.9
A217: L0568 | B217: Neha Joshi | C217: 30 | D217: Male | E217: Delhi | F217: Business | G217: =YEAR(Table1[[#This Row],[Application_Date]]) -> 2024 | H217: =TEXT(Table1[[#This Row],[EMI_payment_date]],"mmmm") -> December | I217: 45597 | J217: =EDATE(Table1[[#This Row],[Application_Date]],1) -> 45627 | K217: 7404000 | L217: =Table1[[#This Row],[Annual_Income]]/12 -> 617000 | M217: 7604000 | N217: =DATEDIF(Table1[[#This Row],[EMI_payment_date]],TODAY(),"m") -> 19 | P217: 7.9 | Q217: =Table1[[#This Row],[monthly_income]]*30% -> 185100 | R217: =ROUNDUP(NPER(P217/100/12,-Q217,Table1[[#This Row],[Loan_Amount]]),0) -> 49 | S217: 655 | T217: Late | U217: =IF(Table1[[#This Row],[Repayment_Status]]="late","bad loan","good loan") -> bad loan | V217: =IF(Table1[[#This Row],[Repayment_Status]]="late","high","low") -> high | W217: =(Table1[[#This Row],[monthly_EMI]]/Table1[[#This Row],[monthly_income]])*100 -> 30 | X217: 27841.18
A218: L0421 | B218: Arjun Singh | C218: 38 | D218: Male | E218: Chennai | F218: Education | G218: =YEAR(Table1[[#This Row],[Application_Date]]) -> 2024 | H218: =TEXT(Table1[[#This Row],[EMI_payment_date]],"mmmm") -> December | I218: 45598 | J218: =EDATE(Table1[[#This Row],[Application_Date]],1) -> 45628 | K218: 5640000 | L218: =Table1[[#This Row],[Annual_Income]]/12 -> 470000 | M218: 5840000 | N218: =DATEDIF(Table1[[#This Row],[EMI_payment_date]],TODAY(),"m") -> 19 | P218: 8.65 | Q218: =Table1[[#This Row],[monthly_income]]*30% -> 141000 | R218: =ROUNDUP(NPER(P218/100/12,-Q218,Table1[[#This Row],[Loan_Amount]]),0) -> 50 | S218: 713 | T218: Completed | U218: =IF(Table1[[#This Row],[Repayment_Status]]="late","bad loan","good loan") -> good loan | V218: =IF(Table1[[#This Row],[Repayment_Status]]="late","high","low") -> low | W218: =(Table1[[#This Row],[monthly_EMI]]/Table1[[#This Row],[monthly_income]])*100 -> 30 | X218: 31383.07
A219: L0605 | B219: Ritika Patel | C219: 50 | D219: Female | E219: Pune | F219: Home | G219: =YEAR(Table1[[#This Row],[Application_Date]]) -> 2024 | H219: =TEXT(Table1[[#This Row],[EMI_payment_date]],"mmmm") -> December | I219: 45599 | J219: =EDATE(Table1[[#This Row],[Application_Date]],1) -> 45629 | K219: 7848000 | L219: =Table1[[#This Row],[Annual_Income]]/12 -> 654000 | M219: 8048000 | N219: =DATEDIF(Table1[[#This Row],[EMI_payment_date]],TODAY(),"m") -> 19 | P219: 8.46 | Q219: =Table1[[#This Row],[monthly_income]]*30% -> 196200 | R219: =ROUNDUP(NPER(P219/100/12,-Q219,Table1[[#This Row],[Loan_Amount]]),0) -> 49 | S219: 847 | T219: Completed | U219: =IF(Table1[[#This Row],[Repayment_Status]]="late","bad loan","good loan") -> good loan | V219: =IF(Table1[[#This Row],[Repayment_Status]]="late","high","low") -> low | W219: =(Table1[[#This Row],[monthly_EMI]]/Table1[[#This Row],[monthly_income]])*100 -> 30 | X219: 23390
A220: L0002 | B220: Pooja Singh | C220: 24 | D220: Male | E220: Mumbai | F220: Car | G220: =YEAR(Table1[[#This Row],[Application_Date]]) -> 2024 | H220: =TEXT(Table1[[#This Row],[EMI_payment_date]],"mmmm") -> December | I220: 45600 | J220: =EDATE(Table1[[#This Row],[Application_Date]],1) -> 45630 | K220: 612000 | L220: =Table1[[#This Row],[Annual_Income]]/12 -> 51000 | M220: 812000 | N220: =DATEDIF(Table1[[#This Row],[EMI_payment_date]],TODAY(),"m") -> 19 | P220: 8.75 | Q220: =Table1[[#This Row],[monthly_income]]*30% -> 15300 | R220: =ROUNDUP(NPER(P220/100/12,-Q220,Table1[[#This Row],[Loan_Amount]]),0) -> 68 | S220: 755 | T220: Completed | U220: =IF(Table1[[#This Row],[Repayment_Status]]="late","bad loan","good loan") -> good loan | V220: =IF(Table1[[#This Row],[Repayment_Status]]="late","high","low") -> low | W220: =(Table1[[#This Row],[monthly_EMI]]/Table1[[#This Row],[monthly_income]])*100 -> 30 | X220: 20566.53
A221: L0032 | B221: Arjun Verma | C221: 25 | D221: Male | E221: Pune | F221: Car | G221: =YEAR(Table1[[#This Row],[Application_Date]]) -> 2024 | H221: =TEXT(Table1[[#This Row],[EMI_payment_date]],"mmmm") -> December | I221: 45601 | J221: =EDATE(Table1[[#This Row],[Application_Date]],1) -> 45631 | K221: 972000 | L221: =Table1[[#This Row],[Annual_Income]]/12 -> 81000 | M221: 1172000 | N221: =DATEDIF(Table1[[#This Row],[EMI_payment_date]],TODAY(),"m") -> 19 | O221: =20*Table1[[#This Row],[monthly_EMI]] -> 486000 | P221: 6.34 | Q221: =Table1[[#This Row],[monthly_income]]*30% -> 24300 | R221: =ROUNDUP(NPER(P221/100/12,-Q221,Table1[[#This Row],[Loan_Amount]]),0) -> 56 | S221: 654 | T221: Completed | U221: =IF(Table1[[#This Row],[Repayment_Status]]="late","bad loan","good loan") -> good loan | V221: =IF(Table1[[#This Row],[Repayment_Status]]="late","high","low") -> low | W221: =(Table1[[#This Row],[monthly_EMI]]/Table1[[#This Row],[monthly_income]])*100 -> 30 | X221: 26870.95
A222: L0677 | B222: Aarav Verma | C222: 53 | D222: Female | E222: Mumbai | F222: Home | G222: =YEAR(Table1[[#This Row],[Application_Date]]) -> 2024 | H222: =TEXT(Table1[[#This Row],[EMI_payment_date]],"mmmm") -> December | I222: 45602 | J222: =EDATE(Table1[[#This Row],[Application_Date]],1) -> 45632 | K222: 8712000 | L222: =Table1[[#This Row],[Annual_Income]]/12 -> 726000 | M222: 8912000 | N222: =DATEDIF(Table1[[#This Row],[EMI_payment_date]],TODAY(),"m") -> 19 | O222: =20*Table1[[#This Row],[monthly_EMI]] -> 4356000 | P222: 8.43 | Q222: =Table1[[#This Row],[monthly_income]]*30% -> 217800 | R222: =ROUNDUP(NPER(P222/100/12,-Q222,Table1[[#This Row],[Loan_Amount]]),0) -> 49 | S222: 846 | T222: Completed | U222: =IF(Table1[[#This Row],[Repayment_Status]]="late","bad loan","good loan") -> good loan | V222: =IF(Table1[[#This Row],[Repayment_Status]]="late","high","low") -> low | W222: =(Table1[[#This Row],[monthly_EMI]]/Table1[[#This Row],[monthly_income]])*100 -> 30 | X222: 31009.33
A223: L0314 | B223: Ananya Patel | C223: 25 | D223: Male | E223: Chennai | F223: Home | G223: =YEAR(Table1[[#This Row],[Application_Date]]) -> 2024 | H223: =TEXT(Table1[[#This Row],[EMI_payment_date]],"mmmm") -> December | I223: 45603 | J223: =EDATE(Table1[[#This Row],[Application_Date]],1) -> 45633 | K223: 4356000 | L223: =Table1[[#This Row],[Annual_Income]]/12 -> 363000 | M223: 4556000 | N223: =DATEDIF(Table1[[#This Row],[EMI_payment_date]],TODAY(),"m") -> 19 | O223: =20*Table1[[#This Row],[monthly_EMI]] -> 2178000 | P223: 5.12 | Q223: =Table1[[#This Row],[monthly_income]]*30% -> 108900 | R223: =ROUNDUP(NPER(P223/100/12,-Q223,Table1[[#This Row],[Loan_Amount]]),0) -> 47 | S223: 680 | T223: Late | U223: =IF(Table1[[#This Row],[Repayment_Status]]="late","bad loan","good loan") -> bad loan | V223: =IF(Table1[[#This Row],[Repayment_Status]]="late","high","low") -> high | W223: =(Table1[[#This Row],[monthly_EMI]]/Table1[[#This Row],[monthly_income]])*100 -> 30 | X223: 15509.56
A224: L0643 | B224: Vivaan Sharma | C224: 28 | D224: Male | E224: Delhi | F224: Business | G224: =YEAR(Table1[[#This Row],[Application_Date]]) -> 2024 | H224: =TEXT(Table1[[#This Row],[EMI_payment_date]],"mmmm") -> December | I224: 45604 | J224: =EDATE(Table1[[#This Row],[Application_Date]],1) -> 45634 | K224: 8304000 | L224: =Table1[[#This Row],[Annual_Income]]/12 -> 692000 | M224: 8504000 | N224: =DATEDIF(Table1[[#This Row],[EMI_payment_date]],TODAY(),"m") -> 19 | O224: =20*Table1[[#This Row],[monthly_EMI]] -> 4152000 | P224: 5.29 | Q224: =Table1[[#This Row],[monthly_income]]*30% -> 207600 | R224: =ROUNDUP(NPER(P224/100/12,-Q224,Table1[[#This Row],[Loan_Amount]]),0) -> 46 | S224: 667 | T224: Completed | U224: =IF(Table1[[#This Row],[Repayment_Status]]="late","bad loan","good loan") -> good loan | V224: =IF(Table1[[#This Row],[Repayment_Status]]="late","high","low") -> low | W224: =(Table1[[#This Row],[monthly_EMI]]/Table1[[#This Row],[monthly_income]])*100 -> 30 | X224: 21372.08
A225: L0684 | B225: Ishaan Sharma | C225: 28 | D225: Female | E225: Pune | F225: Car | G225: =YEAR(Table1[[#This Row],[Application_Date]]) -> 2024 | H225: =TEXT(Table1[[#This Row],[EMI_payment_date]],"mmmm") -> December | I225: 45605 | J225: =EDATE(Table1[[#This Row],[Application_Date]],1) -> 45635 | K225: 8796000 | L225: =Table1[[#This Row],[Annual_Income]]/12 -> 733000 | M225: 8996000 | N225: =DATEDIF(Table1[[#This Row],[EMI_payment_date]],TODAY(),"m") -> 19 | O225: =20*Table1[[#This Row],[monthly_EMI]] -> 4398000 | P225: 6.3 | Q225: =Table1[[#This Row],[monthly_income]]*30% -> 219900 | R225: =ROUNDUP(NPER(P225/100/12,-Q225,Table1[[#This Row],[Loan_Amount]]),0) -> 47 | S225: 650 | T225: Completed | U225: =IF(Table1[[#This Row],[Repayment_Status]]="late","bad loan","good loan") -> good loan | V225: =IF(Table1[[#This Row],[Repayment_Status]]="late","high","low") -> low | W225: =(Table1[[#This Row],[monthly_EMI]]/Table1[[#This Row],[monthly_income]])*100 -> 30 | X225: 29648.69
A226: L0427 | B226: Sanya Nair | C226: 30 | D226: Male | E226: Chennai | F226: Home | G226: =YEAR(Table1[[#This Row],[Application_Date]]) -> 2024 | H226: =TEXT(Table1[[#This Row],[EMI_payment_date]],"mmmm") -> December | I226: 45606 | J226: =EDATE(Table1[[#This Row],[Application_Date]],1) -> 45636 | K226: 5712000 | L226: =Table1[[#This Row],[Annual_Income]]/12 -> 476000 | M226: 5912000 | N226: =DATEDIF(Table1[[#This Row],[EMI_payment_date]],TODAY(),"m") -> 19 | O226: =20*Table1[[#This Row],[monthly_EMI]] -> 2856000 | P226: 8.66 | Q226: =Table1[[#This Row],[monthly_income]]*30% -> 142800 | R226: =ROUNDUP(NPER(P226/100/12,-Q226,Table1[[#This Row],[Loan_Amount]]),0) -> 50 | S226: 696 | T226: Late | U226: =IF(Table1[[#This Row],[Repayment_Status]]="late","bad loan","good loan") -> bad loan | V226: =IF(Table1[[#This Row],[Repayment_Status]]="late","high","low") -> high | W226: =(Table1[[#This Row],[monthly_EMI]]/Table1[[#This Row],[monthly_income]])*100 -> 30 | X226: 24105.06
A227: L0323 | B227: Ishaan Singh | C227: 41 | D227: Female | E227: Delhi | F227: Education | G227: =YEAR(Table1[[#This Row],[Application_Date]]) -> 2024 | H227: =TEXT(Table1[[#This Row],[EMI_payment_date]],"mmmm") -> December | I227: 45607 | J227: =EDATE(Table1[[#This Row],[Application_Date]],1) -> 45637 | K227: 4464000 | L227: =Table1[[#This Row],[Annual_Income]]/12 -> 372000 | M227: 4664000 | N227: =DATEDIF(Table1[[#This Row],[EMI_payment_date]],TODAY(),"m") -> 19 | O227: =20*Table1[[#This Row],[monthly_EMI]] -> 2232000 | P227: 6.22 | Q227: =Table1[[#This Row],[monthly_income]]*30% -> 111600 | R227: =ROUNDUP(NPER(P227/100/12,-Q227,Table1[[#This Row],[Loan_Amount]]),0) -> 48 | S227: 795 | T227: Completed | U227: =IF(Table1[[#This Row],[Repayment_Status]]="late","bad loan","good loan") -> good loan | V227: =IF(Table1[[#This Row],[Repayment_Status]]="late","high","low") -> low | W227: =(Table1[[#This Row],[monthly_EMI]]/Table1[[#This Row],[monthly_income]])*100 -> 30 | X227: 14076.54
A228: L0369 | B228: Kavya Nair | C228: 40 | D228: Female | E228: Hyderabad | F228: Business | G228: =YEAR(Table1[[#This Row],[Application_Date]]) -> 2024 | H228: =TEXT(Table1[[#This Row],[EMI_payment_date]],"mmmm") -> December | I228: 45608 | J228: =EDATE(Table1[[#This Row],[Application_Date]],1) -> 45638 | K228: 5016000 | L228: =Table1[[#This Row],[Annual_Income]]/12 -> 418000 | M228: 5216000 | N228: =DATEDIF(Table1[[#This Row],[EMI_payment_date]],TODAY(),"m") -> 19 | O228: =20*Table1[[#This Row],[monthly_EMI]] -> 2508000 | P228: 6.75 | Q228: =Table1[[#This Row],[monthly_income]]*30% -> 125400 | R228: =ROUNDUP(NPER(P228/100/12,-Q228,Table1[[#This Row],[Loan_Amount]]),0) -> 48 | S228: 717 | T228: Late | U228: =IF(Table1[[#This Row],[Repayment_Status]]="late","bad loan","good loan") -> bad loan | V228: =IF(Table1[[#This Row],[Repayment_Status]]="late","high","low") -> high | W228: =(Table1[[#This Row],[monthly_EMI]]/Table1[[#This Row],[monthly_income]])*100 -> 30 | X228: 11695.08
A229: L0675 | B229: Sanya Gupta | C229: 53 | D229: Female | E229: Chennai | F229: Business | G229: =YEAR(Table1[[#This Row],[Application_Date]]) -> 2024 | H229: =TEXT(Table1[[#This Row],[EMI_payment_date]],"mmmm") -> December | I229: 45609 | J229: =EDATE(Table1[[#This Row],[Application_Date]],1) -> 45639 | K229: 8688000 | L229: =Table1[[#This Row],[Annual_Income]]/12 -> 724000 | M229: 8888000 | N229: =DATEDIF(Table1[[#This Row],[EMI_payment_date]],TODAY(),"m") -> 19 | O229: =20*Table1[[#This Row],[monthly_EMI]] -> 4344000 | P229: 8.66 | Q229: =Table1[[#This Row],[monthly_income]]*30% -> 217200 | R229: =ROUNDUP(NPER(P229/100/12,-Q229,Table1[[#This Row],[Loan_Amount]]),0) -> 49 | S229: 827 | T229: Completed | U229: =IF(Table1[[#This Row],[Repayment_Status]]="late","bad loan","good loan") -> good loan | V229: =IF(Table1[[#This Row],[Repayment_Status]]="late","high","low") -> low | W229: =(Table1[[#This Row],[monthly_EMI]]/Table1[[#This Row],[monthly_income]])*100 -> 30 | X229: 6854.06
A230: L0692 | B230: Ritika Singh | C230: 45 | D230: Female | E230: Mumbai | F230: Business | G230: =YEAR(Table1[[#This Row],[Application_Date]]) -> 2024 | H230: =TEXT(Table1[[#This Row],[EMI_payment_date]],"mmmm") -> December | I230: 45610 | J230: =EDATE(Table1[[#This Row],[Application_Date]],1) -> 45640 | K230: 8892000 | L230: =Table1[[#This Row],[Annual_Income]]/12 -> 741000 | M230: 9092000 | N230: =DATEDIF(Table1[[#This Row],[EMI_payment_date]],TODAY(),"m") -> 19 | O230: =20*Table1[[#This Row],[monthly_EMI]] -> 4446000 | P230: 7.14 | Q230: =Table1[[#This Row],[monthly_income]]*30% -> 222300 | R230: =ROUNDUP(NPER(P230/100/12,-Q230,Table1[[#This Row],[Loan_Amount]]),0) -> 48 | S230: 795 | T230: Completed | U230: =IF(Table1[[#This Row],[Repayment_Status]]="late","bad loan","good loan") -> good loan | V230: =IF(Table1[[#This Row],[Repayment_Status]]="late","high","low") -> low | W230: =(Table1[[#This Row],[monthly_EMI]]/Table1[[#This Row],[monthly_income]])*100 -> 30 | X230: 21982.52
A231: L0289 | B231: Aarav Kumar | C231: 51 | D231: Female | E231: Chennai | F231: Home | G231: =YEAR(Table1[[#This Row],[Application_Date]]) -> 2024 | H231: =TEXT(Table1[[#This Row],[EMI_payment_date]],"mmmm") -> December | I231: 45611 | J231: =EDATE(Table1[[#This Row],[Application_Date]],1) -> 45641 | K231: 4056000 | L231: =Table1[[#This Row],[Annual_Income]]/12 -> 338000 | M231: 4256000 | N231: =DATEDIF(Table1[[#This Row],[EMI_payment_date]],TODAY(),"m") -> 19 | O231: =20*Table1[[#This Row],[monthly_EMI]] -> 2028000 | P231: 7.36 | Q231: =Table1[[#This Row],[monthly_income]]*30% -> 101400 | R231: =ROUNDUP(NPER(P231/100/12,-Q231,Table1[[#This Row],[Loan_Amount]]),0) -> 49 | S231: 742 | T231: Completed | U231: =IF(Table1[[#This Row],[Repayment_Status]]="late","bad loan","good loan") -> good loan | V231: =IF(Table1[[#This Row],[Repayment_Status]]="late","high","low") -> low | W231: =(Table1[[#This Row],[monthly_EMI]]/Table1[[#This Row],[monthly_income]])*100 -> 30 | X231: 33182.71
A232: L0094 | B232: Aryan Joshi | C232: 56 | D232: Male | E232: Bengaluru | F232: Business | G232: =YEAR(Table1[[#This Row],[Application_Date]]) -> 2024 | H232: =TEXT(Table1[[#This Row],[EMI_payment_date]],"mmmm") -> December | I232: 45612 | J232: =EDATE(Table1[[#This Row],[Application_Date]],1) -> 45642 | K232: 1716000 | L232: =Table1[[#This Row],[Annual_Income]]/12 -> 143000 | M232: 1916000 | N232: =DATEDIF(Table1[[#This Row],[EMI_payment_date]],TODAY(),"m") -> 19 | O232: =20*Table1[[#This Row],[monthly_EMI]] -> 858000 | P232: 6.2 | Q232: =Table1[[#This Row],[monthly_income]]*30% -> 42900 | R232: =ROUNDUP(NPER(P232/100/12,-Q232,Table1[[#This Row],[Loan_Amount]]),0) -> 51 | S232: 752 | T232: Completed | U232: =IF(Table1[[#This Row],[Repayment_Status]]="late","bad loan","good loan") -> good loan | V232: =IF(Table1[[#This Row],[Repayment_Status]]="late","high","low") -> low | W232: =(Table1[[#This Row],[monthly_EMI]]/Table1[[#This Row],[monthly_income]])*100 -> 30 | X232: 22244.94
... A246: L0447 | B246: Aditya Sharma | C246: 50 | D246: Female | E246: Delhi | F246: Personal | G246: =YEAR(Table1[[#This Row],[Application_Date]]) -> 2024 | H246: =TEXT(Table1[[#This Row],[EMI_payment_date]],"mmmm") -> December | I246: 45626 | J246: =EDATE(Table1[[#This Row],[Application_Date]],1) -> 45656 | K246: 5952000 | L246: =Table1[[#This Row],[Annual_Income]]/12 -> 496000 | M246: 6152000 | N246: =DATEDIF(Table1[[#This Row],[EMI_payment_date]],TODAY(),"m") -> 19 | O246: =20*Table1[[#This Row],[monthly_EMI]] -> 2976000 | P246: 6.61 | Q246: =Table1[[#This Row],[monthly_income]]*30% -> 148800 | R246: =ROUNDUP(NPER(P246/100/12,-Q246,Table1[[#This Row],[Loan_Amount]]),0) -> 48 | S246: 714 | T246: Completed | U246: =IF(Table1[[#This Row],[Repayment_Status]]="late","bad loan","good loan") -> good loan | V246: =IF(Table1[[#This Row],[Repayment_Status]]="late","high","low") -> low | W246: =(Table1[[#This Row],[monthly_EMI]]/Table1[[#This Row],[monthly_income]])*100 -> 30 | X246: 16622.17
A247: L0353 | B247: Pooja Joshi | C247: 37 | D247: Female | E247: Delhi | F247: Home | G247: =YEAR(Table1[[#This Row],[Application_Date]]) -> 2024 | H247: =TEXT(Table1[[#This Row],[EMI_payment_date]],"mmmm") -> January | I247: 45627 | J247: =EDATE(Table1[[#This Row],[Application_Date]],1) -> 45658 | K247: 4824000 | L247: =Table1[[#This Row],[Annual_Income]]/12 -> 402000 | M247: 5024000 | N247: =DATEDIF(Table1[[#This Row],[EMI_payment_date]],TODAY(),"m") -> 18 | O247: =19*Table1[[#This Row],[monthly_EMI]] -> 2291400 | P247: 5.07 | Q247: =Table1[[#This Row],[monthly_income]]*30% -> 120600 | R247: =ROUNDUP(NPER(P247/100/12,-Q247,Table1[[#This Row],[Loan_Amount]]),0) -> 46 | S247: 785 | T247: Completed | U247: =IF(Table1[[#This Row],[Repayment_Status]]="late","bad loan","good loan") -> good loan | V247: =IF(Table1[[#This Row],[Repayment_Status]]="late","high","low") -> low | W247: =(Table1[[#This Row],[monthly_EMI]]/Table1[[#This Row],[monthly_income]])*100 -> 30 | X247: 5837.2
A248: L0291 | B248: Sanya Yadav | C248: 56 | D248: Male | E248: Hyderabad | F248: Education | G248: =YEAR(Table1[[#This Row],[Application_Date]]) -> 2024 | H248: =TEXT(Table1[[#This Row],[EMI_payment_date]],"mmmm") -> January | I248: 45628 | J248: =EDATE(Table1[[#This Row],[Application_Date]],1) -> 45659 | K248: 4080000 | L248: =Table1[[#This Row],[Annual_Income]]/12 -> 340000 | M248: 4280000 | N248: =DATEDIF(Table1[[#This Row],[EMI_payment_date]],TODAY(),"m") -> 18 | O248: =19*Table1[[#This Row],[monthly_EMI]] -> 1938000 | P248: 7.55 | Q248: =Table1[[#This Row],[monthly_income]]*30% -> 102000 | R248: =ROUNDUP(NPER(P248/100/12,-Q248,Table1[[#This Row],[Loan_Amount]]),0) -> 49 | S248: 740 | T248: Completed | U248: =IF(Table1[[#This Row],[Repayment_Status]]="late","bad loan","good loan") -> good loan | V248: =IF(Table1[[#This Row],[Repayment_Status]]="late","high","low") -> low | W248: =(Table1[[#This Row],[monthly_EMI]]/Table1[[#This Row],[monthly_income]])*100 -> 30 | X248: 30749.25
A249: L0394 | B249: Meera Yadav | C249: 33 | D249: Female | E249: Delhi | F249: Home | G249: =YEAR(Table1[[#This Row],[Application_Date]]) -> 2024 | H249: =TEXT(Table1[[#This Row],[EMI_payment_date]],"mmmm") -> January | I249: 45629 | J249: =EDATE(Table1[[#This Row],[Application_Date]],1) -> 45660 | K249: 5316000 | L249: =Table1[[#This Row],[Annual_Income]]/12 -> 443000 | M249: 5516000 | N249: =DATEDIF(Table1[[#This Row],[EMI_payment_date]],TODAY(),"m") -> 18 | O249: =19*Table1[[#This Row],[monthly_EMI]] -> 2525100 | P249: 5.58 | Q249: =Table1[[#This Row],[monthly_income]]*30% -> 132900 | R249: =ROUNDUP(NPER(P249/100/12,-Q249,Table1[[#This Row],[Loan_Amount]]),0) -> 47 | S249: 781 | T249: Completed | U249: =IF(Table1[[#This Row],[Repayment_Status]]="late","bad loan","good loan") -> good loan | V249: =IF(Table1[[#This Row],[Repayment_Status]]="late","high","low") -> low | W249: =(Table1[[#This Row],[monthly_EMI]]/Table1[[#This Row],[monthly_income]])*100 -> 30 | X249: 12118.87
A250: L0564 | B250: Pooja Verma | C250: 26 | D250: Female | E250: Delhi | F250: Education | G250: =YEAR(Table1[[#This Row],[Application_Date]]) -> 2024 | H250: =TEXT(Table1[[#This Row],[EMI_payment_date]],"mmmm") -> January | I250: 45630 | J250: =EDATE(Table1[[#This Row],[Application_Date]],1) -> 45661 | K250: 7356000 | L250: =Table1[[#This Row],[Annual_Income]]/12 -> 613000 | M250: 7556000 | N250: =DATEDIF(Table1[[#This Row],[EMI_payment_date]],TODAY(),"m") -> 18 | O250: =19*Table1[[#This Row],[monthly_EMI]] -> 3494100 | P250: 9.68 | Q250: =Table1[[#This Row],[monthly_income]]*30% -> 183900 | R250: =ROUNDUP(NPER(P250/100/12,-Q250,Table1[[#This Row],[Loan_Amount]]),0) -> 51 | S250: 719 | T250: Completed | U250: =IF(Table1[[#This Row],[Repayment_Status]]="late","bad loan","good loan") -> good loan | V250: =IF(Table1[[#This Row],[Repayment_Status]]="late","high","low") -> low | W250: =(Table1[[#This Row],[monthly_EMI]]/Table1[[#This Row],[monthly_income]])*100 -> 30 | X250: 22220.17
A251: L0231 | B251: Kavya Gupta | C251: 41 | D251: Female | E251: Bengaluru | F251: Personal | G251: =YEAR(Table1[[#This Row],[Application_Date]]) -> 2024 | H251: =TEXT(Table1[[#This Row],[EMI_payment_date]],"mmmm") -> January | I251: 45631 | J251: =EDATE(Table1[[#This Row],[Application_Date]],1) -> 45662 | K251: 3360000 | L251: =Table1[[#This Row],[Annual_Income]]/12 -> 280000 | M251: 3560000 | N251: =DATEDIF(Table1[[#This Row],[EMI_payment_date]],TODAY(),"m") -> 18 | O251: =19*Table1[[#This Row],[monthly_EMI]] -> 1596000 | P251: 6.15 | Q251: =Table1[[#This Row],[monthly_income]]*30% -> 84000 | R251: =ROUNDUP(NPER(P251/100/12,-Q251,Table1[[#This Row],[Loan_Amount]]),0) -> 48 | S251: 608 | T251: Completed | U251: =IF(Table1[[#This Row],[Repayment_Status]]="late","bad loan","good loan") -> good loan | V251: =IF(Table1[[#This Row],[Repayment_Status]]="late","high","low") -> low | W251: =(Table1[[#This Row],[monthly_EMI]]/Table1[[#This Row],[monthly_income]])*100 -> 30 | X251: 16377.07
A252: L0187 | B252: Priya Yadav | C252: 24 | D252: Female | E252: Mumbai | F252: Business | G252: =YEAR(Table1[[#This Row],[Application_Date]]) -> 2024 | H252: =TEXT(Table1[[#This Row],[EMI_payment_date]],"mmmm") -> January | I252: 45632 | J252: =EDATE(Table1[[#This Row],[Application_Date]],1) -> 45663 | K252: 2832000 | L252: =Table1[[#This Row],[Annual_Income]]/12 -> 236000 | M252: 3032000 | N252: =DATEDIF(Table1[[#This Row],[EMI_payment_date]],TODAY(),"m") -> 18 | O252: =19*Table1[[#This Row],[monthly_EMI]] -> 1345200 | P252: 6.9 | Q252: =Table1[[#This Row],[monthly_income]]*30% -> 70800 | R252: =ROUNDUP(NPER(P252/100/12,-Q252,Table1[[#This Row],[Loan_Amount]]),0) -> 50 | S252: 686 | T252: Completed | U252: =IF(Table1[[#This Row],[Repayment_Status]]="late","bad loan","good loan") -> good loan | V252: =IF(Table1[[#This Row],[Repayment_Status]]="late","high","low") -> low | W252: =(Table1[[#This Row],[monthly_EMI]]/Table1[[#This Row],[monthly_income]])*100 -> 30 | X252: 19390.31
A253: L0508 | B253: Ananya Verma | C253: 23 | D253: Male | E253: Mumbai | F253: Business | G253: =YEAR(Table1[[#This Row],[Application_Date]]) -> 2024 | H253: =TEXT(Table1[[#This Row],[EMI_payment_date]],"mmmm") -> January | I253: 45633 | J253: =EDATE(Table1[[#This Row],[Application_Date]],1) -> 45664 | K253: 6684000 | L253: =Table1[[#This Row],[Annual_Income]]/12 -> 557000 | M253: 6884000 | N253: =DATEDIF(Table1[[#This Row],[EMI_payment_date]],TODAY(),"m") -> 18 | O253: =19*Table1[[#This Row],[monthly_EMI]] -> 3174900 | P253: 8.57 | Q253: =Table1[[#This Row],[monthly_income]]*30% -> 167100 | R253: =ROUNDUP(NPER(P253/100/12,-Q253,Table1[[#This Row],[Loan_Amount]]),0) -> 49 | S253: 743 | T253: Completed | U253: =IF(Table1[[#This Row],[Repayment_Status]]="late","bad loan","good loan") -> good loan | V253: =IF(Table1[[#This Row],[Repayment_Status]]="late","high","low") -> low | W253: =(Table1[[#This Row],[monthly_EMI]]/Table1[[#This Row],[monthly_income]])*100 -> 30 | X253: 20954.28
A254: L0123 | B254: Ritika Gupta | C254: 28 | D254: Female | E254: Bengaluru | F254: Personal | G254: =YEAR(Table1[[#This Row],[Application_Date]]) -> 2024 | H254: =TEXT(Table1[[#This Row],[EMI_payment_date]],"mmmm") -> January | I254: 45634 | J254: =EDATE(Table1[[#This Row],[Application_Date]],1) -> 45665 | K254: 2064000 | L254: =Table1[[#This Row],[Annual_Income]]/12 -> 172000 | M254: 2264000 | N254: =DATEDIF(Table1[[#This Row],[EMI_payment_date]],TODAY(),"m") -> 18 | O254: =19*Table1[[#This Row],[monthly_EMI]] -> 980400 | P254: 5.85 | Q254: =Table1[[#This Row],[monthly_income]]*30% -> 51600 | R254: =ROUNDUP(NPER(P254/100/12,-Q254,Table1[[#This Row],[Loan_Amount]]),0) -> 50 | S254: 722 | T254: Completed | U254: =IF(Table1[[#This Row],[Repayment_Status]]="late","bad loan","good loan") -> good loan | V254: =IF(Table1[[#This Row],[Repayment_Status]]="late","high","low") -> low | W254: =(Table1[[#This Row],[monthly_EMI]]/Table1[[#This Row],[monthly_income]])*100 -> 30 | X254: 15758.99
A255: L0138 | B255: Sanya Nair | C255: 30 | D255: Female | E255: Bengaluru | F255: Home | G255: =YEAR(Table1[[#This Row],[Application_Date]]) -> 2024 | H255: =TEXT(Table1[[#This Row],[EMI_payment_date]],"mmmm") -> January | I255: 45635 | J255: =EDATE(Table1[[#This Row],[Application_Date]],1) -> 45666 | K255: 2244000 | L255: =Table1[[#This Row],[Annual_Income]]/12 -> 187000 | M255: 2444000 | N255: =DATEDIF(Table1[[#This Row],[EMI_payment_date]],TODAY(),"m") -> 18 | O255: =19*Table1[[#This Row],[monthly_EMI]] -> 1065900 | P255: 8.98 | Q255: =Table1[[#This Row],[monthly_income]]*30% -> 56100 | R255: =ROUNDUP(NPER(P255/100/12,-Q255,Table1[[#This Row],[Loan_Amount]]),0) -> 53 | S255: 661 | T255: Late | U255: =IF(Table1[[#This Row],[Repayment_Status]]="late","bad loan","good loan") -> bad loan | V255: =IF(Table1[[#This Row],[Repayment_Status]]="late","high","low") -> high | W255: =(Table1[[#This Row],[monthly_EMI]]/Table1[[#This Row],[monthly_income]])*100 -> 30 | X255: 37729.78
A256: L0229 | B256: Aditya Kumar | C256: 41 | D256: Male | E256: Delhi | F256: Education | G256: =YEAR(Table1[[#This Row],[Application_Date]]) -> 2024 | H256: =TEXT(Table1[[#This Row],[EMI_payment_date]],"mmmm") -> January | I256: 45636 | J256: =EDATE(Table1[[#This Row],[Application_Date]],1) -> 45667 | K256: 3336000 | L256: =Table1[[#This Row],[Annual_Income]]/12 -> 278000 | M256: 3536000 | N256: =DATEDIF(Table1[[#This Row],[EMI_payment_date]],TODAY(),"m") -> 18 | O256: =19*Table1[[#This Row],[monthly_EMI]] -> 1584600 | P256: 8.49 | Q256: =Table1[[#This Row],[monthly_income]]*30% -> 83400 | R256: =ROUNDUP(NPER(P256/100/12,-Q256,Table1[[#This Row],[Loan_Amount]]),0) -> 51 | S256: 750 | T256: Late | U256: =IF(Table1[[#This Row],[Repayment_Status]]="late","bad loan","good loan") -> bad loan | V256: =IF(Table1[[#This Row],[Repayment_Status]]="late","high","low") -> high | W256: =(Table1[[#This Row],[monthly_EMI]]/Table1[[#This Row],[monthly_income]])*100 -> 30 | X256: 19486.33
A257: L0292 | B257: Rahul Patel | C257: 58 | D257: Male | E257: Mumbai | F257: Business | G257: =YEAR(Table1[[#This Row],[Application_Date]]) -> 2024 | H257: =TEXT(Table1[[#This Row],[EMI_payment_date]],"mmmm") -> January | I257: 45637 | J257: =EDATE(Table1[[#This Row],[Application_Date]],1) -> 45668 | K257: 4092000 | L257: =Table1[[#This Row],[Annual_Income]]/12 -> 341000 | M257: 4292000 | N257: =DATEDIF(Table1[[#This Row],[EMI_payment_date]],TODAY(),"m") -> 18 | O257: =19*Table1[[#This Row],[monthly_EMI]] -> 1943700 | P257: 7.84 | Q257: =Table1[[#This Row],[monthly_income]]*30% -> 102300 | R257: =ROUNDUP(NPER(P257/100/12,-Q257,Table1[[#This Row],[Loan_Amount]]),0) -> 50 | S257: 777 | T257: Late | U257: =IF(Table1[[#This Row],[Repayment_Status]]="late","bad loan","good loan") -> bad loan | V257: =IF(Table1[[#This Row],[Repayment_Status]]="late","high","low") -> high | W257: =(Table1[[#This Row],[monthly_EMI]]/Table1[[#This Row],[monthly_income]])*100 -> 30 | X257: 18822.27
A258: L0698 | B258: Sanya Verma | C258: 38 | D258: Male | E258: Delhi | F258: Business | G258: =YEAR(Table1[[#This Row],[Application_Date]]) -> 2024 | H258: =TEXT(Table1[[#This Row],[EMI_payment_date]],"mmmm") -> January | I258: 45638 | J258: =EDATE(Table1[[#This Row],[Application_Date]],1) -> 45669 | K258: 8964000 | L258: =Table1[[#This Row],[Annual_Income]]/12 -> 747000 | M258: 9164000 | N258: =DATEDIF(Table1[[#This Row],[EMI_payment_date]],TODAY(),"m") -> 18 | O258: =19*Table1[[#This Row],[monthly_EMI]] -> 4257900 | P258: 6.9 | Q258: =Table1[[#This Row],[monthly_income]]*30% -> 224100 | R258: =ROUNDUP(NPER(P258/100/12,-Q258,Table1[[#This Row],[Loan_Amount]]),0) -> 47 | S258: 675 | T258: Completed | U258: =IF(Table1[[#This Row],[Repayment_Status]]="late","bad loan","good loan") -> good loan | V258: =IF(Table1[[#This Row],[Repayment_Status]]="late","high","low") -> low | W258: =(Table1[[#This Row],[monthly_EMI]]/Table1[[#This Row],[monthly_income]])*100 -> 30 | X258: 23780.27
... A277: L0261 | B277: Ritika Joshi | C277: 52 | D277: Female | E277: Delhi | F277: Car | G277: =YEAR(Table1[[#This Row],[Application_Date]]) -> 2024 | H277: =TEXT(Table1[[#This Row],[EMI_payment_date]],"mmmm") -> January | I277: 45657 | J277: =EDATE(Table1[[#This Row],[Application_Date]],1) -> 45688 | K277: 3720000 | L277: =Table1[[#This Row],[Annual_Income]]/12 -> 310000 | M277: 3920000 | N277: =DATEDIF(Table1[[#This Row],[EMI_payment_date]],TODAY(),"m") -> 17 | O277: =19*Table1[[#This Row],[monthly_EMI]] -> 1767000 | P277: 9.42 | Q277: =Table1[[#This Row],[monthly_income]]*30% -> 93000 | R277: =ROUNDUP(NPER(P277/100/12,-Q277,Table1[[#This Row],[Loan_Amount]]),0) -> 52 | S277: 659 | T277: Late | U277: =IF(Table1[[#This Row],[Repayment_Status]]="late","bad loan","good loan") -> bad loan | V277: =IF(Table1[[#This Row],[Repayment_Status]]="late","high","low") -> high | W277: =(Table1[[#This Row],[monthly_EMI]]/Table1[[#This Row],[monthly_income]])*100 -> 30 | X277: 42974.06
A278: L0221 | B278: Sanya Singh | C278: 58 | D278: Male | E278: Chennai | F278: Education | G278: =YEAR(Table1[[#This Row],[Application_Date]]) -> 2025 | H278: =TEXT(Table1[[#This Row],[EMI_payment_date]],"mmmm") -> February | I278: 45658 | J278: =EDATE(Table1[[#This Row],[Application_Date]],1) -> 45689 | K278: 3240000 | L278: =Table1[[#This Row],[Annual_Income]]/12 -> 270000 | M278: 3440000 | N278: =DATEDIF(Table1[[#This Row],[EMI_payment_date]],TODAY(),"m") -> 17 | O278: =18*Table1[[#This Row],[monthly_EMI]] -> 1458000 | P278: 8.62 | Q278: =Table1[[#This Row],[monthly_income]]*30% -> 81000 | R278: =ROUNDUP(NPER(P278/100/12,-Q278,Table1[[#This Row],[Loan_Amount]]),0) -> 51 | S278: 835 | T278: Completed | U278: =IF(Table1[[#This Row],[Repayment_Status]]="late","bad loan","good loan") -> good loan | V278: =IF(Table1[[#This Row],[Repayment_Status]]="late","high","low") -> low | W278: =(Table1[[#This Row],[monthly_EMI]]/Table1[[#This Row],[monthly_income]])*100 -> 30 | X278: 30736.82
A279: L0306 | B279: Rohan Verma | C279: 59 | D279: Female | E279: Pune | F279: Home | G279: =YEAR(Table1[[#This Row],[Application_Date]]) -> 2025 | H279: =TEXT(Table1[[#This Row],[EMI_payment_date]],"mmmm") -> February | I279: 45659 | J279: =EDATE(Table1[[#This Row],[Application_Date]],1) -> 45690 | K279: 4260000 | L279: =Table1[[#This Row],[Annual_Income]]/12 -> 355000 | M279: 4460000 | N279: =DATEDIF(Table1[[#This Row],[EMI_payment_date]],TODAY(),"m") -> 17 | O279: =18*Table1[[#This Row],[monthly_EMI]] -> 1917000 | P279: 8.29 | Q279: =Table1[[#This Row],[monthly_income]]*30% -> 106500 | R279: =ROUNDUP(NPER(P279/100/12,-Q279,Table1[[#This Row],[Loan_Amount]]),0) -> 50 | S279: 699 | T279: Late | U279: =IF(Table1[[#This Row],[Repayment_Status]]="late","bad loan","good loan") -> bad loan | V279: =IF(Table1[[#This Row],[Repayment_Status]]="late","high","low") -> high | W279: =(Table1[[#This Row],[monthly_EMI]]/Table1[[#This Row],[monthly_income]])*100 -> 30 | X279: 25597.76
A280: L0645 | B280: Aisha Patel | C280: 55 | D280: Male | E280: Bengaluru | F280: Personal | G280: =YEAR(Table1[[#This Row],[Application_Date]]) -> 2025 | H280: =TEXT(Table1[[#This Row],[EMI_payment_date]],"mmmm") -> February | I280: 45660 | J280: =EDATE(Table1[[#This Row],[Application_Date]],1) -> 45691 | K280: 8328000 | L280: =Table1[[#This Row],[Annual_Income]]/12 -> 694000 | M280: 8528000 | N280: =DATEDIF(Table1[[#This Row],[EMI_payment_date]],TODAY(),"m") -> 17 | O280: =18*Table1[[#This Row],[monthly_EMI]] -> 3747600 | P280: 6.31 | Q280: =Table1[[#This Row],[monthly_income]]*30% -> 208200 | R280: =ROUNDUP(NPER(P280/100/12,-Q280,Table1[[#This Row],[Loan_Amount]]),0) -> 47 | S280: 687 | T280: Late | U280: =IF(Table1[[#This Row],[Repayment_Status]]="late","bad loan","good loan") -> bad loan | V280: =IF(Table1[[#This Row],[Repayment_Status]]="late","high","low") -> high | W280: =(Table1[[#This Row],[monthly_EMI]]/Table1[[#This Row],[monthly_income]])*100 -> 30 | X280: 22882.8
A281: L0440 | B281: Neha Joshi | C281: 39 | D281: Male | E281: Pune | F281: Business | G281: =YEAR(Table1[[#This Row],[Application_Date]]) -> 2025 | H281: =TEXT(Table1[[#This Row],[EMI_payment_date]],"mmmm") -> February | I281: 45661 | J281: =EDATE(Table1[[#This Row],[Application_Date]],1) -> 45692 | K281: 5868000 | L281: =Table1[[#This Row],[Annual_Income]]/12 -> 489000 | M281: 6068000 | N281: =DATEDIF(Table1[[#This Row],[EMI_payment_date]],TODAY(),"m") -> 17 | O281: =18*Table1[[#This Row],[monthly_EMI]] -> 2640600 | P281: 7.73 | Q281: =Table1[[#This Row],[monthly_income]]*30% -> 146700 | R281: =ROUNDUP(NPER(P281/100/12,-Q281,Table1[[#This Row],[Loan_Amount]]),0) -> 49 | S281: 678 | T281: Completed | U281: =IF(Table1[[#This Row],[Repayment_Status]]="late","bad loan","good loan") -> good loan | V281: =IF(Table1[[#This Row],[Repayment_Status]]="late","high","low") -> low | W281: =(Table1[[#This Row],[monthly_EMI]]/Table1[[#This Row],[monthly_income]])*100 -> 30 | X281: 30770.9
A282: L0284 | B282: Aisha Singh | C282: 23 | D282: Male | E282: Mumbai | F282: Home | G282: =YEAR(Table1[[#This Row],[Application_Date]]) -> 2025 | H282: =TEXT(Table1[[#This Row],[EMI_payment_date]],"mmmm") -> February | I282: 45662 | J282: =EDATE(Table1[[#This Row],[Application_Date]],1) -> 45693 | K282: 3996000 | L282: =Table1[[#This Row],[Annual_Income]]/12 -> 333000 | M282: 4196000 | N282: =DATEDIF(Table1[[#This Row],[EMI_payment_date]],TODAY(),"m") -> 17 | O282: =18*Table1[[#This Row],[monthly_EMI]] -> 1798200 | P282: 9.11 | Q282: =Table1[[#This Row],[monthly_income]]*30% -> 99900 | R282: =ROUNDUP(NPER(P282/100/12,-Q282,Table1[[#This Row],[Loan_Amount]]),0) -> 51 | S282: 812 | T282: Completed | U282: =IF(Table1[[#This Row],[Repayment_Status]]="late","bad loan","good loan") -> good loan | V282: =IF(Table1[[#This Row],[Repayment_Status]]="late","high","low") -> low | W282: =(Table1[[#This Row],[monthly_EMI]]/Table1[[#This Row],[monthly_income]])*100 -> 30 | X282: 34684.34
A283: L0234 | B283: Sanya Mehta | C283: 49 | D283: Female | E283: Pune | F283: Car | G283: =YEAR(Table1[[#This Row],[Application_Date]]) -> 2025 | H283: =TEXT(Table1[[#This Row],[EMI_payment_date]],"mmmm") -> February | I283: 45663 | J283: =EDATE(Table1[[#This Row],[Application_Date]],1) -> 45694 | K283: 3396000 | L283: =Table1[[#This Row],[Annual_Income]]/12 -> 283000 | M283: 3596000 | N283: =DATEDIF(Table1[[#This Row],[EMI_payment_date]],TODAY(),"m") -> 17 | O283: =18*Table1[[#This Row],[monthly_EMI]] -> 1528200 | P283: 7.69 | Q283: =Table1[[#This Row],[monthly_income]]*30% -> 84900 | R283: =ROUNDUP(NPER(P283/100/12,-Q283,Table1[[#This Row],[Loan_Amount]]),0) -> 50 | S283: 610 | T283: Completed | U283: =IF(Table1[[#This Row],[Repayment_Status]]="late","bad loan","good loan") -> good loan | V283: =IF(Table1[[#This Row],[Repayment_Status]]="late","high","low") -> low | W283: =(Table1[[#This Row],[monthly_EMI]]/Table1[[#This Row],[monthly_income]])*100 -> 30 | X283: 25689.52
A284: L0683 | B284: Rohan Nair | C284: 34 | D284: Male | E284: Chennai | F284: Car | G284: =YEAR(Table1[[#This Row],[Application_Date]]) -> 2025 | H284: =TEXT(Table1[[#This Row],[EMI_payment_date]],"mmmm") -> February | I284: 45664 | J284: =EDATE(Table1[[#This Row],[Application_Date]],1) -> 45695 | K284: 8784000 | L284: =Table1[[#This Row],[Annual_Income]]/12 -> 732000 | M284: 8984000 | N284: =DATEDIF(Table1[[#This Row],[EMI_payment_date]],TODAY(),"m") -> 17 | O284: =18*Table1[[#This Row],[monthly_EMI]] -> 3952800 | P284: 8.28 | Q284: =Table1[[#This Row],[monthly_income]]*30% -> 219600 | R284: =ROUNDUP(NPER(P284/100/12,-Q284,Table1[[#This Row],[Loan_Amount]]),0) -> 49 | S284: 850 | T284: Completed | U284: =IF(Table1[[#This Row],[Repayment_Status]]="late","bad loan","good loan") -> good loan | V284: =IF(Table1[[#This Row],[Repayment_Status]]="late","high","low") -> low | W284: =(Table1[[#This Row],[monthly_EMI]]/Table1[[#This Row],[monthly_income]])*100 -> 30 | X284: 30462.57
A285: L0374 | B285: Aditya Kumar | C285: 37 | D285: Female | E285: Delhi | F285: Personal | G285: =YEAR(Table1[[#This Row],[Application_Date]]) -> 2025 | H285: =TEXT(Table1[[#This Row],[EMI_payment_date]],"mmmm") -> February | I285: 45665 | J285: =EDATE(Table1[[#This Row],[Application_Date]],1) -> 45696 | K285: 5076000 | L285: =Table1[[#This Row],[Annual_Income]]/12 -> 423000 | M285: 5276000 | N285: =DATEDIF(Table1[[#This Row],[EMI_payment_date]],TODAY(),"m") -> 17 | O285: =18*Table1[[#This Row],[monthly_EMI]] -> 2284200 | P285: 8.61 | Q285: =Table1[[#This Row],[monthly_income]]*30% -> 126900 | R285: =ROUNDUP(NPER(P285/100/12,-Q285,Table1[[#This Row],[Loan_Amount]]),0) -> 50 | S285: 693 | T285: Completed | U285: =IF(Table1[[#This Row],[Repayment_Status]]="late","bad loan","good loan") -> good loan | V285: =IF(Table1[[#This Row],[Repayment_Status]]="late","high","low") -> low | W285: =(Table1[[#This Row],[monthly_EMI]]/Table1[[#This Row],[monthly_income]])*100 -> 30 | X285: 31713.87
A286: L0052 | B286: Aarav Nair | C286: 27 | D286: Male | E286: Chennai | F286: Home | G286: =YEAR(Table1[[#This Row],[Application_Date]]) -> 2025 | H286: =TEXT(Table1[[#This Row],[EMI_payment_date]],"mmmm") -> February | I286: 45666 | J286: =EDATE(Table1[[#This Row],[Application_Date]],1) -> 45697 | K286: 1212000 | L286: =Table1[[#This Row],[Annual_Income]]/12 -> 101000 | M286: 1412000 | N286: =DATEDIF(Table1[[#This Row],[EMI_payment_date]],TODAY(),"m") -> 17 | O286: =18*Table1[[#This Row],[monthly_EMI]] -> 545400 | P286: 5.7 | Q286: =Table1[[#This Row],[monthly_income]]*30% -> 30300 | R286: =ROUNDUP(NPER(P286/100/12,-Q286,Table1[[#This Row],[Loan_Amount]]),0) -> 53 | S286: 834 | T286: Completed | U286: =IF(Table1[[#This Row],[Repayment_Status]]="late","bad loan","good loan") -> good loan | V286: =IF(Table1[[#This Row],[Repayment_Status]]="late","high","low") -> low | W286: =(Table1[[#This Row],[monthly_EMI]]/Table1[[#This Row],[monthly_income]])*100 -> 30 | X286: 19476.23
A287: L0144 | B287: Arjun Nair | C287: 41 | D287: Male | E287: Bengaluru | F287: Home | G287: =YEAR(Table1[[#This Row],[Application_Date]]) -> 2025 | H287: =TEXT(Table1[[#This Row],[EMI_payment_date]],"mmmm") -> February | I287: 45667 | J287: =EDATE(Table1[[#This Row],[Application_Date]],1) -> 45698 | K287: 2316000 | L287: =Table1[[#This Row],[Annual_Income]]/12 -> 193000 | M287: 2516000 | N287: =DATEDIF(Table1[[#This Row],[EMI_payment_date]],TODAY(),"m") -> 17 | O287: =18*Table1[[#This Row],[monthly_EMI]] -> 1042200 | P287: 8.72 | Q287: =Table1[[#This Row],[monthly_income]]*30% -> 57900 | R287: =ROUNDUP(NPER(P287/100/12,-Q287,Table1[[#This Row],[Loan_Amount]]),0) -> 53 | S287: 706 | T287: Completed | U287: =IF(Table1[[#This Row],[Repayment_Status]]="late","bad loan","good loan") -> good loan | V287: =IF(Table1[[#This Row],[Repayment_Status]]="late","high","low") -> low | W287: =(Table1[[#This Row],[monthly_EMI]]/Table1[[#This Row],[monthly_income]])*100 -> 30 | X287: 19376.07
A288: L0493 | B288: Kavya Sharma | C288: 60 | D288: Female | E288: Bengaluru | F288: Home | G288: =YEAR(Table1[[#This Row],[Application_Date]]) -> 2025 | H288: =TEXT(Table1[[#This Row],[EMI_payment_date]],"mmmm") -> February | I288: 45668 | J288: =EDATE(Table1[[#This Row],[Application_Date]],1) -> 45699 | K288: 6504000 | L288: =Table1[[#This Row],[Annual_Income]]/12 -> 542000 | M288: 6704000 | N288: =DATEDIF(Table1[[#This Row],[EMI_payment_date]],TODAY(),"m") -> 17 | O288: =18*Table1[[#This Row],[monthly_EMI]] -> 2926800 | P288: 6.29 | Q288: =Table1[[#This Row],[monthly_income]]*30% -> 162600 | R288: =ROUNDUP(NPER(P288/100/12,-Q288,Table1[[#This Row],[Loan_Amount]]),0) -> 47 | S288: 681 | T288: Completed | U288: =IF(Table1[[#This Row],[Repayment_Status]]="late","bad loan","good loan") -> good loan | V288: =IF(Table1[[#This Row],[Repayment_Status]]="late","high","low") -> low | W288: =(Table1[[#This Row],[monthly_EMI]]/Table1[[#This Row],[monthly_income]])*100 -> 30 | X288: 6259.56
A289: L0529 | B289: Priya Singh | C289: 30 | D289: Male | E289: Bengaluru | F289: Home | G289: =YEAR(Table1[[#This Row],[Application_Date]]) -> 2025 | H289: =TEXT(Table1[[#This Row],[EMI_payment_date]],"mmmm") -> February | I289: 45669 | J289: =EDATE(Table1[[#This Row],[Application_Date]],1) -> 45700 | K289: 6936000 | L289: =Table1[[#This Row],[Annual_Income]]/12 -> 578000 | M289: 7136000 | N289: =DATEDIF(Table1[[#This Row],[EMI_payment_date]],TODAY(),"m") -> 17 | O289: =18*Table1[[#This Row],[monthly_EMI]] -> 3121200 | P289: 5.82 | Q289: =Table1[[#This Row],[monthly_income]]*30% -> 173400 | R289: =ROUNDUP(NPER(P289/100/12,-Q289,Table1[[#This Row],[Loan_Amount]]),0) -> 47 | S289: 749 | T289: Completed | U289: =IF(Table1[[#This Row],[Repayment_Status]]="late","bad loan","good loan") -> good loan | V289: =IF(Table1[[#This Row],[Repayment_Status]]="late","high","low") -> low | W289: =(Table1[[#This Row],[monthly_EMI]]/Table1[[#This Row],[monthly_income]])*100 -> 30 | X289: 22715.98
... A308: L0342 | B308: Aryan Yadav | C308: 26 | D308: Female | E308: Bengaluru | F308: Education | G308: =YEAR(Table1[[#This Row],[Application_Date]]) -> 2025 | H308: =TEXT(Table1[[#This Row],[EMI_payment_date]],"mmmm") -> February | I308: 45688 | J308: =EDATE(Table1[[#This Row],[Application_Date]],1) -> 45716 | K308: 4692000 | L308: =Table1[[#This Row],[Annual_Income]]/12 -> 391000 | M308: 4892000 | N308: =DATEDIF(Table1[[#This Row],[EMI_payment_date]],TODAY(),"m") -> 17 | O308: =18*Table1[[#This Row],[monthly_EMI]] -> 2111400 | P308: 7.63 | Q308: =Table1[[#This Row],[monthly_income]]*30% -> 117300 | R308: =ROUNDUP(NPER(P308/100/12,-Q308,Table1[[#This Row],[Loan_Amount]]),0) -> 49 | S308: 643 | T308: Completed | U308: =IF(Table1[[#This Row],[Repayment_Status]]="late","bad loan","good loan") -> good loan | V308: =IF(Table1[[#This Row],[Repayment_Status]]="late","high","low") -> low | W308: =(Table1[[#This Row],[monthly_EMI]]/Table1[[#This Row],[monthly_income]])*100 -> 30 | X308: 15758.99
A309: L0616 | B309: Aryan Joshi | C309: 49 | D309: Female | E309: Delhi | F309: Personal | G309: =YEAR(Table1[[#This Row],[Application_Date]]) -> 2025 | H309: =TEXT(Table1[[#This Row],[EMI_payment_date]],"mmmm") -> March | I309: 45689 | J309: =EDATE(Table1[[#This Row],[Application_Date]],1) -> 45717 | K309: 7980000 | L309: =Table1[[#This Row],[Annual_Income]]/12 -> 665000 | M309: 8180000 | N309: =DATEDIF(Table1[[#This Row],[EMI_payment_date]],TODAY(),"m") -> 16 | O309: =17*Table1[[#This Row],[monthly_EMI]] -> 3391500 | P309: 5.44 | Q309: =Table1[[#This Row],[monthly_income]]*30% -> 199500 | R309: =ROUNDUP(NPER(P309/100/12,-Q309,Table1[[#This Row],[Loan_Amount]]),0) -> 46 | S309: 691 | T309: Late | U309: =IF(Table1[[#This Row],[Repayment_Status]]="late","bad loan","good loan") -> bad loan | V309: =IF(Table1[[#This Row],[Repayment_Status]]="late","high","low") -> high | W309: =(Table1[[#This Row],[monthly_EMI]]/Table1[[#This Row],[monthly_income]])*100 -> 30 | X309: 7801.69
A310: L0036 | B310: Rohan Yadav | C310: 34 | D310: Female | E310: Mumbai | F310: Car | G310: =YEAR(Table1[[#This Row],[Application_Date]]) -> 2025 | H310: =TEXT(Table1[[#This Row],[EMI_payment_date]],"mmmm") -> March | I310: 45690 | J310: =EDATE(Table1[[#This Row],[Application_Date]],1) -> 45718 | K310: 1020000 | L310: =Table1[[#This Row],[Annual_Income]]/12 -> 85000 | M310: 1220000 | N310: =DATEDIF(Table1[[#This Row],[EMI_payment_date]],TODAY(),"m") -> 16 | O310: =17*Table1[[#This Row],[monthly_EMI]] -> 433500 | P310: 5.25 | Q310: =Table1[[#This Row],[monthly_income]]*30% -> 25500 | R310: =ROUNDUP(NPER(P310/100/12,-Q310,Table1[[#This Row],[Loan_Amount]]),0) -> 54 | S310: 824 | T310: Completed | U310: =IF(Table1[[#This Row],[Repayment_Status]]="late","bad loan","good loan") -> good loan | V310: =IF(Table1[[#This Row],[Repayment_Status]]="late","high","low") -> low | W310: =(Table1[[#This Row],[monthly_EMI]]/Table1[[#This Row],[monthly_income]])*100 -> 30 | X310: 11730.26
A311: L0311 | B311: Priya Singh | C311: 26 | D311: Female | E311: Chennai | F311: Education | G311: =YEAR(Table1[[#This Row],[Application_Date]]) -> 2025 | H311: =TEXT(Table1[[#This Row],[EMI_payment_date]],"mmmm") -> March | I311: 45691 | J311: =EDATE(Table1[[#This Row],[Application_Date]],1) -> 45719 | K311: 4320000 | L311: =Table1[[#This Row],[Annual_Income]]/12 -> 360000 | M311: 4520000 | N311: =DATEDIF(Table1[[#This Row],[EMI_payment_date]],TODAY(),"m") -> 16 | O311: =17*Table1[[#This Row],[monthly_EMI]] -> 1836000 | P311: 7.4 | Q311: =Table1[[#This Row],[monthly_income]]*30% -> 108000 | R311: =ROUNDUP(NPER(P311/100/12,-Q311,Table1[[#This Row],[Loan_Amount]]),0) -> 49 | S311: 697 | T311: Completed | U311: =IF(Table1[[#This Row],[Repayment_Status]]="late","bad loan","good loan") -> good loan | V311: =IF(Table1[[#This Row],[Repayment_Status]]="late","high","low") -> low | W311: =(Table1[[#This Row],[monthly_EMI]]/Table1[[#This Row],[monthly_income]])*100 -> 30 | X311: 22415.41
A312: L0230 | B312: Priya Singh | C312: 54 | D312: Female | E312: Mumbai | F312: Business | G312: =YEAR(Table1[[#This Row],[Application_Date]]) -> 2025 | H312: =TEXT(Table1[[#This Row],[EMI_payment_date]],"mmmm") -> March | I312: 45692 | J312: =EDATE(Table1[[#This Row],[Application_Date]],1) -> 45720 | K312: 3348000 | L312: =Table1[[#This Row],[Annual_Income]]/12 -> 279000 | M312: 3548000 | N312: =DATEDIF(Table1[[#This Row],[EMI_payment_date]],TODAY(),"m") -> 16 | O312: =17*Table1[[#This Row],[monthly_EMI]] -> 1422900 | P312: 9.49 | Q312: =Table1[[#This Row],[monthly_income]]*30% -> 83700 | R312: =ROUNDUP(NPER(P312/100/12,-Q312,Table1[[#This Row],[Loan_Amount]]),0) -> 52 | S312: 833 | T312: Late | U312: =IF(Table1[[#This Row],[Repayment_Status]]="late","bad loan","good loan") -> bad loan | V312: =IF(Table1[[#This Row],[Repayment_Status]]="late","high","low") -> high | W312: =(Table1[[#This Row],[monthly_EMI]]/Table1[[#This Row],[monthly_income]])*100 -> 30 | X312: 35253.34
A313: L0251 | B313: Aditya Joshi | C313: 47 | D313: Female | E313: Delhi | F313: Home | G313: =YEAR(Table1[[#This Row],[Application_Date]]) -> 2025 | H313: =TEXT(Table1[[#This Row],[EMI_payment_date]],"mmmm") -> March | I313: 45693 | J313: =EDATE(Table1[[#This Row],[Application_Date]],1) -> 45721 | K313: 3600000 | L313: =Table1[[#This Row],[Annual_Income]]/12 -> 300000 | M313: 3800000 | N313: =DATEDIF(Table1[[#This Row],[EMI_payment_date]],TODAY(),"m") -> 16 | O313: =17*Table1[[#This Row],[monthly_EMI]] -> 1530000 | P313: 5.03 | Q313: =Table1[[#This Row],[monthly_income]]*30% -> 90000 | R313: =ROUNDUP(NPER(P313/100/12,-Q313,Table1[[#This Row],[Loan_Amount]]),0) -> 47 | S313: 627 | T313: Late | U313: =IF(Table1[[#This Row],[Repayment_Status]]="late","bad loan","good loan") -> bad loan | V313: =IF(Table1[[#This Row],[Repayment_Status]]="late","high","low") -> high | W313: =(Table1[[#This Row],[monthly_EMI]]/Table1[[#This Row],[monthly_income]])*100 -> 30 | X313: 20796.79
A314: L0033 | B314: Aisha Kumar | C314: 34 | D314: Male | E314: Delhi | F314: Car | G314: =YEAR(Table1[[#This Row],[Application_Date]]) -> 2025 | H314: =TEXT(Table1[[#This Row],[EMI_payment_date]],"mmmm") -> March | I314: 45694 | J314: =EDATE(Table1[[#This Row],[Application_Date]],1) -> 45722 | K314: 984000 | L314: =Table1[[#This Row],[Annual_Income]]/12 -> 82000 | M314: 1184000 | N314: =DATEDIF(Table1[[#This Row],[EMI_payment_date]],TODAY(),"m") -> 16 | O314: =17*Table1[[#This Row],[monthly_EMI]] -> 418200 | P314: 5.88 | Q314: =Table1[[#This Row],[monthly_income]]*30% -> 24600 | R314: =ROUNDUP(NPER(P314/100/12,-Q314,Table1[[#This Row],[Loan_Amount]]),0) -> 56 | S314: 766 | T314: Completed | U314: =IF(Table1[[#This Row],[Repayment_Status]]="late","bad loan","good loan") -> good loan | V314: =IF(Table1[[#This Row],[Repayment_Status]]="late","high","low") -> low | W314: =(Table1[[#This Row],[monthly_EMI]]/Table1[[#This Row],[monthly_income]])*100 -> 30 | X314: 24958.11
A315: L0055 | B315: Kavya Sharma | C315: 36 | D315: Male | E315: Chennai | F315: Business | G315: =YEAR(Table1[[#This Row],[Application_Date]]) -> 2025 | H315: =TEXT(Table1[[#This Row],[EMI_payment_date]],"mmmm") -> March | I315: 45695 | J315: =EDATE(Table1[[#This Row],[Application_Date]],1) -> 45723 | K315: 1248000 | L315: =Table1[[#This Row],[Annual_Income]]/12 -> 104000 | M315: 1448000 | N315: =DATEDIF(Table1[[#This Row],[EMI_payment_date]],TODAY(),"m") -> 16 | O315: =17*Table1[[#This Row],[monthly_EMI]] -> 530400 | P315: 6.1 | Q315: =Table1[[#This Row],[monthly_income]]*30% -> 31200 | R315: =ROUNDUP(NPER(P315/100/12,-Q315,Table1[[#This Row],[Loan_Amount]]),0) -> 54 | S315: 752 | T315: Completed | U315: =IF(Table1[[#This Row],[Repayment_Status]]="late","bad loan","good loan") -> good loan | V315: =IF(Table1[[#This Row],[Repayment_Status]]="late","high","low") -> low | W315: =(Table1[[#This Row],[monthly_EMI]]/Table1[[#This Row],[monthly_income]])*100 -> 30 | X315: 17189.01
A316: L0456 | B316: Arjun Patel | C316: 28 | D316: Male | E316: Delhi | F316: Business | G316: =YEAR(Table1[[#This Row],[Application_Date]]) -> 2025 | H316: =TEXT(Table1[[#This Row],[EMI_payment_date]],"mmmm") -> March | I316: 45696 | J316: =EDATE(Table1[[#This Row],[Application_Date]],1) -> 45724 | K316: 6060000 | L316: =Table1[[#This Row],[Annual_Income]]/12 -> 505000 | M316: 6260000 | N316: =DATEDIF(Table1[[#This Row],[EMI_payment_date]],TODAY(),"m") -> 16 | O316: =17*Table1[[#This Row],[monthly_EMI]] -> 2575500 | P316: 7.4 | Q316: =Table1[[#This Row],[monthly_income]]*30% -> 151500 | R316: =ROUNDUP(NPER(P316/100/12,-Q316,Table1[[#This Row],[Loan_Amount]]),0) -> 48 | S316: 600 | T316: Completed | U316: =IF(Table1[[#This Row],[Repayment_Status]]="late","bad loan","good loan") -> good loan | V316: =IF(Table1[[#This Row],[Repayment_Status]]="late","high","low") -> low | W316: =(Table1[[#This Row],[monthly_EMI]]/Table1[[#This Row],[monthly_income]])*100 -> 30 | X316: 12480.07
A317: L0145 | B317: Sneha Sharma | C317: 32 | D317: Female | E317: Bengaluru | F317: Education | G317: =YEAR(Table1[[#This Row],[Application_Date]]) -> 2025 | H317: =TEXT(Table1[[#This Row],[EMI_payment_date]],"mmmm") -> March | I317: 45697 | J317: =EDATE(Table1[[#This Row],[Application_Date]],1) -> 45725 | K317: 2328000 | L317: =Table1[[#This Row],[Annual_Income]]/12 -> 194000 | M317: 2528000 | N317: =DATEDIF(Table1[[#This Row],[EMI_payment_date]],TODAY(),"m") -> 16 | O317: =17*Table1[[#This Row],[monthly_EMI]] -> 989400 | P317: 8.93 | Q317: =Table1[[#This Row],[monthly_income]]*30% -> 58200 | R317: =ROUNDUP(NPER(P317/100/12,-Q317,Table1[[#This Row],[Loan_Amount]]),0) -> 53 | S317: 667 | T317: Completed | U317: =IF(Table1[[#This Row],[Repayment_Status]]="late","bad loan","good loan") -> good loan | V317: =IF(Table1[[#This Row],[Repayment_Status]]="late","high","low") -> low | W317: =(Table1[[#This Row],[monthly_EMI]]/Table1[[#This Row],[monthly_income]])*100 -> 30 | X317: 12155.55
A318: L0118 | B318: Pooja Gupta | C318: 47 | D318: Male | E318: Hyderabad | F318: Education | G318: =YEAR(Table1[[#This Row],[Application_Date]]) -> 2025 | H318: =TEXT(Table1[[#This Row],[EMI_payment_date]],"mmmm") -> March | I318: 45698 | J318: =EDATE(Table1[[#This Row],[Application_Date]],1) -> 45726 | K318: 2004000 | L318: =Table1[[#This Row],[Annual_Income]]/12 -> 167000 | M318: 2204000 | N318: =DATEDIF(Table1[[#This Row],[EMI_payment_date]],TODAY(),"m") -> 16 | O318: =17*Table1[[#This Row],[monthly_EMI]] -> 851700 | P318: 8.87 | Q318: =Table1[[#This Row],[monthly_income]]*30% -> 50100 | R318: =ROUNDUP(NPER(P318/100/12,-Q318,Table1[[#This Row],[Loan_Amount]]),0) -> 54 | S318: 753 | T318: Completed | U318: =IF(Table1[[#This Row],[Repayment_Status]]="late","bad loan","good loan") -> good loan | V318: =IF(Table1[[#This Row],[Repayment_Status]]="late","high","low") -> low | W318: =(Table1[[#This Row],[monthly_EMI]]/Table1[[#This Row],[monthly_income]])*100 -> 30 | X318: 23174.84
A319: L0169 | B319: Diya Nair | C319: 47 | D319: Female | E319: Delhi | F319: Education | G319: =YEAR(Table1[[#This Row],[Application_Date]]) -> 2025 | H319: =TEXT(Table1[[#This Row],[EMI_payment_date]],"mmmm") -> March | I319: 45699 | J319: =EDATE(Table1[[#This Row],[Application_Date]],1) -> 45727 | K319: 2616000 | L319: =Table1[[#This Row],[Annual_Income]]/12 -> 218000 | M319: 2816000 | N319: =DATEDIF(Table1[[#This Row],[EMI_payment_date]],TODAY(),"m") -> 16 | O319: =17*Table1[[#This Row],[monthly_EMI]] -> 1111800 | P319: 8.88 | Q319: =Table1[[#This Row],[monthly_income]]*30% -> 65400 | R319: =ROUNDUP(NPER(P319/100/12,-Q319,Table1[[#This Row],[Loan_Amount]]),0) -> 53 | S319: 838 | T319: Late | U319: =IF(Table1[[#This Row],[Repayment_Status]]="late","bad loan","good loan") -> bad loan | V319: =IF(Table1[[#This Row],[Repayment_Status]]="late","high","low") -> high | W319: =(Table1[[#This Row],[monthly_EMI]]/Table1[[#This Row],[monthly_income]])*100 -> 30 | X319: 26786.29
A320: L0337 | B320: Aisha Singh | C320: 49 | D320: Female | E320: Pune | F320: Home | G320: =YEAR(Table1[[#This Row],[Application_Date]]) -> 2025 | H320: =TEXT(Table1[[#This Row],[EMI_payment_date]],"mmmm") -> March | I320: 45700 | J320: =EDATE(Table1[[#This Row],[Application_Date]],1) -> 45728 | K320: 4632000 | L320: =Table1[[#This Row],[Annual_Income]]/12 -> 386000 | M320: 4832000 | N320: =DATEDIF(Table1[[#This Row],[EMI_payment_date]],TODAY(),"m") -> 16 | O320: =17*Table1[[#This Row],[monthly_EMI]] -> 1968600 | P320: 8.82 | Q320: =Table1[[#This Row],[monthly_income]]*30% -> 115800 | R320: =ROUNDUP(NPER(P320/100/12,-Q320,Table1[[#This Row],[Loan_Amount]]),0) -> 51 | S320: 813 | T320: Late | U320: =IF(Table1[[#This Row],[Repayment_Status]]="late","bad loan","good loan") -> bad loan | V320: =IF(Table1[[#This Row],[Repayment_Status]]="late","high","low") -> high | W320: =(Table1[[#This Row],[monthly_EMI]]/Table1[[#This Row],[monthly_income]])*100 -> 30 | X320: 36994.96
... A336: L0631 | B336: Sneha Gupta | C336: 29 | D336: Male | E336: Pune | F336: Education | G336: =YEAR(Table1[[#This Row],[Application_Date]]) -> 2025 | H336: =TEXT(Table1[[#This Row],[EMI_payment_date]],"mmmm") -> March | I336: 45716 | J336: =EDATE(Table1[[#This Row],[Application_Date]],1) -> 45744 | K336: 8160000 | L336: =Table1[[#This Row],[Annual_Income]]/12 -> 680000 | M336: 8360000 | N336: =DATEDIF(Table1[[#This Row],[EMI_payment_date]],TODAY(),"m") -> 16 | O336: =17*Table1[[#This Row],[monthly_EMI]] -> 3468000 | P336: 6.29 | Q336: =Table1[[#This Row],[monthly_income]]*30% -> 204000 | R336: =ROUNDUP(NPER(P336/100/12,-Q336,Table1[[#This Row],[Loan_Amount]]),0) -> 47 | S336: 778 | T336: Late | U336: =IF(Table1[[#This Row],[Repayment_Status]]="late","bad loan","good loan") -> bad loan | V336: =IF(Table1[[#This Row],[Repayment_Status]]="late","high","low") -> high | W336: =(Table1[[#This Row],[monthly_EMI]]/Table1[[#This Row],[monthly_income]])*100 -> 30 | X336: 15860.44
A337: L0227 | B337: Ritika Mehta | C337: 52 | D337: Male | E337: Delhi | F337: Home | G337: =YEAR(Table1[[#This Row],[Application_Date]]) -> 2025 | H337: =TEXT(Table1[[#This Row],[EMI_payment_date]],"mmmm") -> April | I337: 45717 | J337: =EDATE(Table1[[#This Row],[Application_Date]],1) -> 45748 | K337: 3312000 | L337: =Table1[[#This Row],[Annual_Income]]/12 -> 276000 | M337: 3512000 | N337: =DATEDIF(Table1[[#This Row],[EMI_payment_date]],TODAY(),"m") -> 15 | O337: =16*Table1[[#This Row],[monthly_EMI]] -> 1324800 | P337: 9.12 | Q337: =Table1[[#This Row],[monthly_income]]*30% -> 82800 | R337: =ROUNDUP(NPER(P337/100/12,-Q337,Table1[[#This Row],[Loan_Amount]]),0) -> 52 | S337: 781 | T337: Late | U337: =IF(Table1[[#This Row],[Repayment_Status]]="late","bad loan","good loan") -> bad loan | V337: =IF(Table1[[#This Row],[Repayment_Status]]="late","high","low") -> high | W337: =(Table1[[#This Row],[monthly_EMI]]/Table1[[#This Row],[monthly_income]])*100 -> 30 | X337: 17824.84
A338: L0125 | B338: Arjun Joshi | C338: 53 | D338: Female | E338: Hyderabad | F338: Home | G338: =YEAR(Table1[[#This Row],[Application_Date]]) -> 2025 | H338: =TEXT(Table1[[#This Row],[EMI_payment_date]],"mmmm") -> April | I338: 45718 | J338: =EDATE(Table1[[#This Row],[Application_Date]],1) -> 45749 | K338: 2088000 | L338: =Table1[[#This Row],[Annual_Income]]/12 -> 174000 | M338: 2288000 | N338: =DATEDIF(Table1[[#This Row],[EMI_payment_date]],TODAY(),"m") -> 15 | O338: =16*Table1[[#This Row],[monthly_EMI]] -> 835200 | P338: 5.2 | Q338: =Table1[[#This Row],[monthly_income]]*30% -> 52200 | R338: =ROUNDUP(NPER(P338/100/12,-Q338,Table1[[#This Row],[Loan_Amount]]),0) -> 49 | S338: 738 | T338: Completed | U338: =IF(Table1[[#This Row],[Repayment_Status]]="late","bad loan","good loan") -> good loan | V338: =IF(Table1[[#This Row],[Repayment_Status]]="late","high","low") -> low | W338: =(Table1[[#This Row],[monthly_EMI]]/Table1[[#This Row],[monthly_income]])*100 -> 30 | X338: 9212.18
A339: L0158 | B339: Karan Joshi | C339: 51 | D339: Female | E339: Mumbai | F339: Home | G339: =YEAR(Table1[[#This Row],[Application_Date]]) -> 2025 | H339: =TEXT(Table1[[#This Row],[EMI_payment_date]],"mmmm") -> April | I339: 45719 | J339: =EDATE(Table1[[#This Row],[Application_Date]],1) -> 45750 | K339: 2484000 | L339: =Table1[[#This Row],[Annual_Income]]/12 -> 207000 | M339: 2684000 | N339: =DATEDIF(Table1[[#This Row],[EMI_payment_date]],TODAY(),"m") -> 15 | O339: =16*Table1[[#This Row],[monthly_EMI]] -> 993600 | P339: 7.3 | Q339: =Table1[[#This Row],[monthly_income]]*30% -> 62100 | R339: =ROUNDUP(NPER(P339/100/12,-Q339,Table1[[#This Row],[Loan_Amount]]),0) -> 51 | S339: 812 | T339: Completed | U339: =IF(Table1[[#This Row],[Repayment_Status]]="late","bad loan","good loan") -> good loan | V339: =IF(Table1[[#This Row],[Repayment_Status]]="late","high","low") -> low | W339: =(Table1[[#This Row],[monthly_EMI]]/Table1[[#This Row],[monthly_income]])*100 -> 30 | X339: 13958.11
A340: L0336 | B340: Meera Sharma | C340: 42 | D340: Male | E340: Bengaluru | F340: Business | G340: =YEAR(Table1[[#This Row],[Application_Date]]) -> 2025 | H340: =TEXT(Table1[[#This Row],[EMI_payment_date]],"mmmm") -> April | I340: 45720 | J340: =EDATE(Table1[[#This Row],[Application_Date]],1) -> 45751 | K340: 4620000 | L340: =Table1[[#This Row],[Annual_Income]]/12 -> 385000 | M340: 4820000 | N340: =DATEDIF(Table1[[#This Row],[EMI_payment_date]],TODAY(),"m") -> 15 | O340: =16*Table1[[#This Row],[monthly_EMI]] -> 1848000 | P340: 9.83 | Q340: =Table1[[#This Row],[monthly_income]]*30% -> 115500 | R340: =ROUNDUP(NPER(P340/100/12,-Q340,Table1[[#This Row],[Loan_Amount]]),0) -> 52 | S340: 663 | T340: Completed | U340: =IF(Table1[[#This Row],[Repayment_Status]]="late","bad loan","good loan") -> good loan | V340: =IF(Table1[[#This Row],[Repayment_Status]]="late","high","low") -> low | W340: =(Table1[[#This Row],[monthly_EMI]]/Table1[[#This Row],[monthly_income]])*100 -> 30 | X340: 18274.85
A341: L0542 | B341: Neha Patel | C341: 50 | D341: Male | E341: Mumbai | F341: Personal | G341: =YEAR(Table1[[#This Row],[Application_Date]]) -> 2025 | H341: =TEXT(Table1[[#This Row],[EMI_payment_date]],"mmmm") -> April | I341: 45721 | J341: =EDATE(Table1[[#This Row],[Application_Date]],1) -> 45752 | K341: 7092000 | L341: =Table1[[#This Row],[Annual_Income]]/12 -> 591000 | M341: 7292000 | N341: =DATEDIF(Table1[[#This Row],[EMI_payment_date]],TODAY(),"m") -> 15 | O341: =16*Table1[[#This Row],[monthly_EMI]] -> 2836800 | P341: 9.1 | Q341: =Table1[[#This Row],[monthly_income]]*30% -> 177300 | R341: =ROUNDUP(NPER(P341/100/12,-Q341,Table1[[#This Row],[Loan_Amount]]),0) -> 50 | S341: 756 | T341: Completed | U341: =IF(Table1[[#This Row],[Repayment_Status]]="late","bad loan","good loan") -> good loan | V341: =IF(Table1[[#This Row],[Repayment_Status]]="late","high","low") -> low | W341: =(Table1[[#This Row],[monthly_EMI]]/Table1[[#This Row],[monthly_income]])*100 -> 30 | X341: 44255.05
A342: L0450 | B342: Rohan Nair | C342: 49 | D342: Male | E342: Bengaluru | F342: Personal | G342: =YEAR(Table1[[#This Row],[Application_Date]]) -> 2025 | H342: =TEXT(Table1[[#This Row],[EMI_payment_date]],"mmmm") -> April | I342: 45722 | J342: =EDATE(Table1[[#This Row],[Application_Date]],1) -> 45753 | K342: 5988000 | L342: =Table1[[#This Row],[Annual_Income]]/12 -> 499000 | M342: 6188000 | N342: =DATEDIF(Table1[[#This Row],[EMI_payment_date]],TODAY(),"m") -> 15 | O342: =16*Table1[[#This Row],[monthly_EMI]] -> 2395200 | P342: 9.67 | Q342: =Table1[[#This Row],[monthly_income]]*30% -> 149700 | R342: =ROUNDUP(NPER(P342/100/12,-Q342,Table1[[#This Row],[Loan_Amount]]),0) -> 51 | S342: 775 | T342: Late | U342: =IF(Table1[[#This Row],[Repayment_Status]]="late","bad loan","good loan") -> bad loan | V342: =IF(Table1[[#This Row],[Repayment_Status]]="late","high","low") -> high | W342: =(Table1[[#This Row],[monthly_EMI]]/Table1[[#This Row],[monthly_income]])*100 -> 30 | X342: 24534.59
A343: L0209 | B343: Neha Nair | C343: 30 | D343: Female | E343: Bengaluru | F343: Business | G343: =YEAR(Table1[[#This Row],[Application_Date]]) -> 2025 | H343: =TEXT(Table1[[#This Row],[EMI_payment_date]],"mmmm") -> April | I343: 45723 | J343: =EDATE(Table1[[#This Row],[Application_Date]],1) -> 45754 | K343: 3096000 | L343: =Table1[[#This Row],[Annual_Income]]/12 -> 258000 | M343: 3296000 | N343: =DATEDIF(Table1[[#This Row],[EMI_payment_date]],TODAY(),"m") -> 15 | O343: =16*Table1[[#This Row],[monthly_EMI]] -> 1238400 | P343: 9.12 | Q343: =Table1[[#This Row],[monthly_income]]*30% -> 77400 | R343: =ROUNDUP(NPER(P343/100/12,-Q343,Table1[[#This Row],[Loan_Amount]]),0) -> 52 | S343: 764 | T343: Late | U343: =IF(Table1[[#This Row],[Repayment_Status]]="late","bad loan","good loan") -> bad loan | V343: =IF(Table1[[#This Row],[Repayment_Status]]="late","high","low") -> high | W343: =(Table1[[#This Row],[monthly_EMI]]/Table1[[#This Row],[monthly_income]])*100 -> 30 | X343: 19418.6
A344: L0700 | B344: Kavya Sharma | C344: 47 | D344: Female | E344: Mumbai | F344: Personal | G344: =YEAR(Table1[[#This Row],[Application_Date]]) -> 2025 | H344: =TEXT(Table1[[#This Row],[EMI_payment_date]],"mmmm") -> April | I344: 45724 | J344: =EDATE(Table1[[#This Row],[Application_Date]],1) -> 45755 | K344: 8988000 | L344: =Table1[[#This Row],[Annual_Income]]/12 -> 749000 | M344: 9188000 | N344: =DATEDIF(Table1[[#This Row],[EMI_payment_date]],TODAY(),"m") -> 15 | O344: =16*Table1[[#This Row],[monthly_EMI]] -> 3595200 | P344: 9.92 | Q344: =Table1[[#This Row],[monthly_income]]*30% -> 224700 | R344: =ROUNDUP(NPER(P344/100/12,-Q344,Table1[[#This Row],[Loan_Amount]]),0) -> 51 | S344: 638 | T344: Completed | U344: =IF(Table1[[#This Row],[Repayment_Status]]="late","bad loan","good loan") -> good loan | V344: =IF(Table1[[#This Row],[Repayment_Status]]="late","high","low") -> low | W344: =(Table1[[#This Row],[monthly_EMI]]/Table1[[#This Row],[monthly_income]])*100 -> 30 | X344: 20401.43
A345: L0105 | B345: Aditya Patel | C345: 33 | D345: Male | E345: Hyderabad | F345: Business | G345: =YEAR(Table1[[#This Row],[Application_Date]]) -> 2025 | H345: =TEXT(Table1[[#This Row],[EMI_payment_date]],"mmmm") -> April | I345: 45725 | J345: =EDATE(Table1[[#This Row],[Application_Date]],1) -> 45756 | K345: 1848000 | L345: =Table1[[#This Row],[Annual_Income]]/12 -> 154000 | M345: 2048000 | N345: =DATEDIF(Table1[[#This Row],[EMI_payment_date]],TODAY(),"m") -> 15 | O345: =16*Table1[[#This Row],[monthly_EMI]] -> 739200 | P345: 9.94 | Q345: =Table1[[#This Row],[monthly_income]]*30% -> 46200 | R345: =ROUNDUP(NPER(P345/100/12,-Q345,Table1[[#This Row],[Loan_Amount]]),0) -> 56 | S345: 624 | T345: Late | U345: =IF(Table1[[#This Row],[Repayment_Status]]="late","bad loan","good loan") -> bad loan | V345: =IF(Table1[[#This Row],[Repayment_Status]]="late","high","low") -> high | W345: =(Table1[[#This Row],[monthly_EMI]]/Table1[[#This Row],[monthly_income]])*100 -> 30 | X345: 21085.09
A346: L0300 | B346: Neha Patel | C346: 40 | D346: Male | E346: Bengaluru | F346: Business | G346: =YEAR(Table1[[#This Row],[Application_Date]]) -> 2025 | H346: =TEXT(Table1[[#This Row],[EMI_payment_date]],"mmmm") -> April | I346: 45726 | J346: =EDATE(Table1[[#This Row],[Application_Date]],1) -> 45757 | K346: 4188000 | L346: =Table1[[#This Row],[Annual_Income]]/12 -> 349000 | M346: 4388000 | N346: =DATEDIF(Table1[[#This Row],[EMI_payment_date]],TODAY(),"m") -> 15 | O346: =16*Table1[[#This Row],[monthly_EMI]] -> 1675200 | P346: 7.65 | Q346: =Table1[[#This Row],[monthly_income]]*30% -> 104700 | R346: =ROUNDUP(NPER(P346/100/12,-Q346,Table1[[#This Row],[Loan_Amount]]),0) -> 49 | S346: 765 | T346: Late | U346: =IF(Table1[[#This Row],[Repayment_Status]]="late","bad loan","good loan") -> bad loan | V346: =IF(Table1[[#This Row],[Repayment_Status]]="late","high","low") -> high | W346: =(Table1[[#This Row],[monthly_EMI]]/Table1[[#This Row],[monthly_income]])*100 -> 30 | X346: 9212.74
A347: L0582 | B347: Ritika Yadav | C347: 59 | D347: Male | E347: Pune | F347: Education | G347: =YEAR(Table1[[#This Row],[Application_Date]]) -> 2025 | H347: =TEXT(Table1[[#This Row],[EMI_payment_date]],"mmmm") -> April | I347: 45727 | J347: =EDATE(Table1[[#This Row],[Application_Date]],1) -> 45758 | K347: 7572000 | L347: =Table1[[#This Row],[Annual_Income]]/12 -> 631000 | M347: 7772000 | N347: =DATEDIF(Table1[[#This Row],[EMI_payment_date]],TODAY(),"m") -> 15 | O347: =16*Table1[[#This Row],[monthly_EMI]] -> 3028800 | P347: 9.16 | Q347: =Table1[[#This Row],[monthly_income]]*30% -> 189300 | R347: =ROUNDUP(NPER(P347/100/12,-Q347,Table1[[#This Row],[Loan_Amount]]),0) -> 50 | S347: 794 | T347: Completed | U347: =IF(Table1[[#This Row],[Repayment_Status]]="late","bad loan","good loan") -> good loan | V347: =IF(Table1[[#This Row],[Repayment_Status]]="late","high","low") -> low | W347: =(Table1[[#This Row],[monthly_EMI]]/Table1[[#This Row],[monthly_income]])*100 -> 30 | X347: 19796.52
A348: L0607 | B348: Sanya Kumar | C348: 25 | D348: Male | E348: Pune | F348: Personal | G348: =YEAR(Table1[[#This Row],[Application_Date]]) -> 2025 | H348: =TEXT(Table1[[#This Row],[EMI_payment_date]],"mmmm") -> April | I348: 45728 | J348: =EDATE(Table1[[#This Row],[Application_Date]],1) -> 45759 | K348: 7872000 | L348: =Table1[[#This Row],[Annual_Income]]/12 -> 656000 | M348: 8072000 | N348: =DATEDIF(Table1[[#This Row],[EMI_payment_date]],TODAY(),"m") -> 15 | O348: =16*Table1[[#This Row],[monthly_EMI]] -> 3148800 | P348: 8.86 | Q348: =Table1[[#This Row],[monthly_income]]*30% -> 196800 | R348: =ROUNDUP(NPER(P348/100/12,-Q348,Table1[[#This Row],[Loan_Amount]]),0) -> 50 | S348: 741 | T348: Completed | U348: =IF(Table1[[#This Row],[Repayment_Status]]="late","bad loan","good loan") -> good loan | V348: =IF(Table1[[#This Row],[Repayment_Status]]="late","high","low") -> low | W348: =(Table1[[#This Row],[monthly_EMI]]/Table1[[#This Row],[monthly_income]])*100 -> 30 | X348: 36110.6
... A367: L0400 | B367: Ishaan Verma | C367: 30 | D367: Male | E367: Hyderabad | F367: Car | G367: =YEAR(Table1[[#This Row],[Application_Date]]) -> 2025 | H367: =TEXT(Table1[[#This Row],[EMI_payment_date]],"mmmm") -> April | I367: 45747 | J367: =EDATE(Table1[[#This Row],[Application_Date]],1) -> 45777 | K367: 5388000 | L367: =Table1[[#This Row],[Annual_Income]]/12 -> 449000 | M367: 5588000 | N367: =DATEDIF(Table1[[#This Row],[EMI_payment_date]],TODAY(),"m") -> 15 | O367: =16*Table1[[#This Row],[monthly_EMI]] -> 2155200 | P367: 7.1 | Q367: =Table1[[#This Row],[monthly_income]]*30% -> 134700 | R367: =ROUNDUP(NPER(P367/100/12,-Q367,Table1[[#This Row],[Loan_Amount]]),0) -> 48 | S367: 663 | T367: Late | U367: =IF(Table1[[#This Row],[Repayment_Status]]="late","bad loan","good loan") -> bad loan | V367: =IF(Table1[[#This Row],[Repayment_Status]]="late","high","low") -> high | W367: =(Table1[[#This Row],[monthly_EMI]]/Table1[[#This Row],[monthly_income]])*100 -> 30 | X367: 9539.15
A368: L0403 | B368: Ananya Gupta | C368: 54 | D368: Female | E368: Pune | F368: Personal | G368: =YEAR(Table1[[#This Row],[Application_Date]]) -> 2025 | H368: =TEXT(Table1[[#This Row],[EMI_payment_date]],"mmmm") -> May | I368: 45748 | J368: =EDATE(Table1[[#This Row],[Application_Date]],1) -> 45778 | K368: 5424000 | L368: =Table1[[#This Row],[Annual_Income]]/12 -> 452000 | M368: 5624000 | N368: =DATEDIF(Table1[[#This Row],[EMI_payment_date]],TODAY(),"m") -> 14 | O368: =15*Table1[[#This Row],[monthly_EMI]] -> 2034000 | P368: 5.21 | Q368: =Table1[[#This Row],[monthly_income]]*30% -> 135600 | R368: =ROUNDUP(NPER(P368/100/12,-Q368,Table1[[#This Row],[Loan_Amount]]),0) -> 46 | S368: 766 | T368: Completed | U368: =IF(Table1[[#This Row],[Repayment_Status]]="late","bad loan","good loan") -> good loan | V368: =IF(Table1[[#This Row],[Repayment_Status]]="late","high","low") -> low | W368: =(Table1[[#This Row],[monthly_EMI]]/Table1[[#This Row],[monthly_income]])*100 -> 30 | X368: 22621.6
A369: L0499 | B369: Karan Verma | C369: 55 | D369: Female | E369: Chennai | F369: Education | G369: =YEAR(Table1[[#This Row],[Application_Date]]) -> 2025 | H369: =TEXT(Table1[[#This Row],[EMI_payment_date]],"mmmm") -> May | I369: 45749 | J369: =EDATE(Table1[[#This Row],[Application_Date]],1) -> 45779 | K369: 6576000 | L369: =Table1[[#This Row],[Annual_Income]]/12 -> 548000 | M369: 6776000 | N369: =DATEDIF(Table1[[#This Row],[EMI_payment_date]],TODAY(),"m") -> 14 | O369: =15*Table1[[#This Row],[monthly_EMI]] -> 2466000 | P369: 8.02 | Q369: =Table1[[#This Row],[monthly_income]]*30% -> 164400 | R369: =ROUNDUP(NPER(P369/100/12,-Q369,Table1[[#This Row],[Loan_Amount]]),0) -> 49 | S369: 715 | T369: Late | U369: =IF(Table1[[#This Row],[Repayment_Status]]="late","bad loan","good loan") -> bad loan | V369: =IF(Table1[[#This Row],[Repayment_Status]]="late","high","low") -> high | W369: =(Table1[[#This Row],[monthly_EMI]]/Table1[[#This Row],[monthly_income]])*100 -> 30 | X369: 25943.18
A370: L0043 | B370: Sneha Joshi | C370: 35 | D370: Male | E370: Hyderabad | F370: Education | G370: =YEAR(Table1[[#This Row],[Application_Date]]) -> 2025 | H370: =TEXT(Table1[[#This Row],[EMI_payment_date]],"mmmm") -> May | I370: 45750 | J370: =EDATE(Table1[[#This Row],[Application_Date]],1) -> 45780 | K370: 1104000 | L370: =Table1[[#This Row],[Annual_Income]]/12 -> 92000 | M370: 1304000 | N370: =DATEDIF(Table1[[#This Row],[EMI_payment_date]],TODAY(),"m") -> 14 | O370: =15*Table1[[#This Row],[monthly_EMI]] -> 414000 | P370: 9.19 | Q370: =Table1[[#This Row],[monthly_income]]*30% -> 27600 | R370: =ROUNDUP(NPER(P370/100/12,-Q370,Table1[[#This Row],[Loan_Amount]]),0) -> 59 | S370: 788 | T370: Completed | U370: =IF(Table1[[#This Row],[Repayment_Status]]="late","bad loan","good loan") -> good loan | V370: =IF(Table1[[#This Row],[Repayment_Status]]="late","high","low") -> low | W370: =(Table1[[#This Row],[monthly_EMI]]/Table1[[#This Row],[monthly_income]])*100 -> 30 | X370: 37581.55
A371: L0487 | B371: Arjun Yadav | C371: 22 | D371: Female | E371: Delhi | F371: Personal | G371: =YEAR(Table1[[#This Row],[Application_Date]]) -> 2025 | H371: =TEXT(Table1[[#This Row],[EMI_payment_date]],"mmmm") -> May | I371: 45751 | J371: =EDATE(Table1[[#This Row],[Application_Date]],1) -> 45781 | K371: 6432000 | L371: =Table1[[#This Row],[Annual_Income]]/12 -> 536000 | M371: 6632000 | N371: =DATEDIF(Table1[[#This Row],[EMI_payment_date]],TODAY(),"m") -> 14 | O371: =15*Table1[[#This Row],[monthly_EMI]] -> 2412000 | P371: 9.15 | Q371: =Table1[[#This Row],[monthly_income]]*30% -> 160800 | R371: =ROUNDUP(NPER(P371/100/12,-Q371,Table1[[#This Row],[Loan_Amount]]),0) -> 50 | S371: 714 | T371: Late | U371: =IF(Table1[[#This Row],[Repayment_Status]]="late","bad loan","good loan") -> bad loan | V371: =IF(Table1[[#This Row],[Repayment_Status]]="late","high","low") -> high | W371: =(Table1[[#This Row],[monthly_EMI]]/Table1[[#This Row],[monthly_income]])*100 -> 30 | X371: 23291.31
A372: L0521 | B372: Aryan Mehta | C372: 60 | D372: Male | E372: Hyderabad | F372: Education | G372: =YEAR(Table1[[#This Row],[Application_Date]]) -> 2025 | H372: =TEXT(Table1[[#This Row],[EMI_payment_date]],"mmmm") -> May | I372: 45752 | J372: =EDATE(Table1[[#This Row],[Application_Date]],1) -> 45782 | K372: 6840000 | L372: =Table1[[#This Row],[Annual_Income]]/12 -> 570000 | M372: 7040000 | N372: =DATEDIF(Table1[[#This Row],[EMI_payment_date]],TODAY(),"m") -> 14 | O372: =15*Table1[[#This Row],[monthly_EMI]] -> 2565000 | P372: 6.94 | Q372: =Table1[[#This Row],[monthly_income]]*30% -> 171000 | R372: =ROUNDUP(NPER(P372/100/12,-Q372,Table1[[#This Row],[Loan_Amount]]),0) -> 48 | S372: 850 | T372: Completed | U372: =IF(Table1[[#This Row],[Repayment_Status]]="late","bad loan","good loan") -> good loan | V372: =IF(Table1[[#This Row],[Repayment_Status]]="late","high","low") -> low | W372: =(Table1[[#This Row],[monthly_EMI]]/Table1[[#This Row],[monthly_income]])*100 -> 30 | X372: 26567.28
A373: L0037 | B373: Meera Singh | C373: 53 | D373: Female | E373: Chennai | F373: Personal | G373: =YEAR(Table1[[#This Row],[Application_Date]]) -> 2025 | H373: =TEXT(Table1[[#This Row],[EMI_payment_date]],"mmmm") -> May | I373: 45753 | J373: =EDATE(Table1[[#This Row],[Application_Date]],1) -> 45783 | K373: 1032000 | L373: =Table1[[#This Row],[Annual_Income]]/12 -> 86000 | M373: 1232000 | N373: =DATEDIF(Table1[[#This Row],[EMI_payment_date]],TODAY(),"m") -> 14 | O373: =15*Table1[[#This Row],[monthly_EMI]] -> 387000 | P373: 8.18 | Q373: =Table1[[#This Row],[monthly_income]]*30% -> 25800 | R373: =ROUNDUP(NPER(P373/100/12,-Q373,Table1[[#This Row],[Loan_Amount]]),0) -> 58 | S373: 611 | T373: Late | U373: =IF(Table1[[#This Row],[Repayment_Status]]="late","bad loan","good loan") -> bad loan | V373: =IF(Table1[[#This Row],[Repayment_Status]]="late","high","low") -> high | W373: =(Table1[[#This Row],[monthly_EMI]]/Table1[[#This Row],[monthly_income]])*100 -> 30 | X373: 24609.74
A374: L0268 | B374: Diya Joshi | C374: 53 | D374: Male | E374: Delhi | F374: Home | G374: =YEAR(Table1[[#This Row],[Application_Date]]) -> 2025 | H374: =TEXT(Table1[[#This Row],[EMI_payment_date]],"mmmm") -> May | I374: 45754 | J374: =EDATE(Table1[[#This Row],[Application_Date]],1) -> 45784 | K374: 3804000 | L374: =Table1[[#This Row],[Annual_Income]]/12 -> 317000 | M374: 4004000 | N374: =DATEDIF(Table1[[#This Row],[EMI_payment_date]],TODAY(),"m") -> 14 | O374: =15*Table1[[#This Row],[monthly_EMI]] -> 1426500 | P374: 6.86 | Q374: =Table1[[#This Row],[monthly_income]]*30% -> 95100 | R374: =ROUNDUP(NPER(P374/100/12,-Q374,Table1[[#This Row],[Loan_Amount]]),0) -> 49 | S374: 728 | T374: Completed | U374: =IF(Table1[[#This Row],[Repayment_Status]]="late","bad loan","good loan") -> good loan | V374: =IF(Table1[[#This Row],[Repayment_Status]]="late","high","low") -> low | W374: =(Table1[[#This Row],[monthly_EMI]]/Table1[[#This Row],[monthly_income]])*100 -> 30 | X374: 22597.32
A375: L0056 | B375: Ananya Sharma | C375: 41 | D375: Female | E375: Bengaluru | F375: Education | G375: =YEAR(Table1[[#This Row],[Application_Date]]) -> 2025 | H375: =TEXT(Table1[[#This Row],[EMI_payment_date]],"mmmm") -> May | I375: 45755 | J375: =EDATE(Table1[[#This Row],[Application_Date]],1) -> 45785 | K375: 1260000 | L375: =Table1[[#This Row],[Annual_Income]]/12 -> 105000 | M375: 1460000 | N375: =DATEDIF(Table1[[#This Row],[EMI_payment_date]],TODAY(),"m") -> 14 | O375: =15*Table1[[#This Row],[monthly_EMI]] -> 472500 | P375: 6.25 | Q375: =Table1[[#This Row],[monthly_income]]*30% -> 31500 | R375: =ROUNDUP(NPER(P375/100/12,-Q375,Table1[[#This Row],[Loan_Amount]]),0) -> 54 | S375: 799 | T375: Completed | U375: =IF(Table1[[#This Row],[Repayment_Status]]="late","bad loan","good loan") -> good loan | V375: =IF(Table1[[#This Row],[Repayment_Status]]="late","high","low") -> low | W375: =(Table1[[#This Row],[monthly_EMI]]/Table1[[#This Row],[monthly_income]])*100 -> 30 | X375: 25556.26
A376: L0408 | B376: Meera Nair | C376: 50 | D376: Male | E376: Bengaluru | F376: Car | G376: =YEAR(Table1[[#This Row],[Application_Date]]) -> 2025 | H376: =TEXT(Table1[[#This Row],[EMI_payment_date]],"mmmm") -> May | I376: 45756 | J376: =EDATE(Table1[[#This Row],[Application_Date]],1) -> 45786 | K376: 5484000 | L376: =Table1[[#This Row],[Annual_Income]]/12 -> 457000 | M376: 5684000 | N376: =DATEDIF(Table1[[#This Row],[EMI_payment_date]],TODAY(),"m") -> 14 | O376: =15*Table1[[#This Row],[monthly_EMI]] -> 2056500 | P376: 6.28 | Q376: =Table1[[#This Row],[monthly_income]]*30% -> 137100 | R376: =ROUNDUP(NPER(P376/100/12,-Q376,Table1[[#This Row],[Loan_Amount]]),0) -> 47 | S376: 775 | T376: Completed | U376: =IF(Table1[[#This Row],[Repayment_Status]]="late","bad loan","good loan") -> good loan | V376: =IF(Table1[[#This Row],[Repayment_Status]]="late","high","low") -> low | W376: =(Table1[[#This Row],[monthly_EMI]]/Table1[[#This Row],[monthly_income]])*100 -> 30 | X376: 20613.36
A377: L0163 | B377: Diya Mehta | C377: 43 | D377: Female | E377: Bengaluru | F377: Home | G377: =YEAR(Table1[[#This Row],[Application_Date]]) -> 2025 | H377: =TEXT(Table1[[#This Row],[EMI_payment_date]],"mmmm") -> May | I377: 45757 | J377: =EDATE(Table1[[#This Row],[Application_Date]],1) -> 45787 | K377: 2544000 | L377: =Table1[[#This Row],[Annual_Income]]/12 -> 212000 | M377: 2744000 | N377: =DATEDIF(Table1[[#This Row],[EMI_payment_date]],TODAY(),"m") -> 14 | O377: =15*Table1[[#This Row],[monthly_EMI]] -> 954000 | P377: 5.18 | Q377: =Table1[[#This Row],[monthly_income]]*30% -> 63600 | R377: =ROUNDUP(NPER(P377/100/12,-Q377,Table1[[#This Row],[Loan_Amount]]),0) -> 48 | S377: 716 | T377: Late | U377: =IF(Table1[[#This Row],[Repayment_Status]]="late","bad loan","good loan") -> bad loan | V377: =IF(Table1[[#This Row],[Repayment_Status]]="late","high","low") -> high | W377: =(Table1[[#This Row],[monthly_EMI]]/Table1[[#This Row],[monthly_income]])*100 -> 30 | X377: 15143.95
A378: L0449 | B378: Sneha Verma | C378: 34 | D378: Female | E378: Bengaluru | F378: Personal | G378: =YEAR(Table1[[#This Row],[Application_Date]]) -> 2025 | H378: =TEXT(Table1[[#This Row],[EMI_payment_date]],"mmmm") -> May | I378: 45758 | J378: =EDATE(Table1[[#This Row],[Application_Date]],1) -> 45788 | K378: 5976000 | L378: =Table1[[#This Row],[Annual_Income]]/12 -> 498000 | M378: 6176000 | N378: =DATEDIF(Table1[[#This Row],[EMI_payment_date]],TODAY(),"m") -> 14 | O378: =15*Table1[[#This Row],[monthly_EMI]] -> 2241000 | P378: 5.84 | Q378: =Table1[[#This Row],[monthly_income]]*30% -> 149400 | R378: =ROUNDUP(NPER(P378/100/12,-Q378,Table1[[#This Row],[Loan_Amount]]),0) -> 47 | S378: 701 | T378: Completed | U378: =IF(Table1[[#This Row],[Repayment_Status]]="late","bad loan","good loan") -> good loan | V378: =IF(Table1[[#This Row],[Repayment_Status]]="late","high","low") -> low | W378: =(Table1[[#This Row],[monthly_EMI]]/Table1[[#This Row],[monthly_income]])*100 -> 30 | X378: 11372.06
A379: L0084 | B379: Neha Patel | C379: 45 | D379: Male | E379: Hyderabad | F379: Education | G379: =YEAR(Table1[[#This Row],[Application_Date]]) -> 2025 | H379: =TEXT(Table1[[#This Row],[EMI_payment_date]],"mmmm") -> May | I379: 45759 | J379: =EDATE(Table1[[#This Row],[Application_Date]],1) -> 45789 | K379: 1596000 | L379: =Table1[[#This Row],[Annual_Income]]/12 -> 133000 | M379: 1796000 | N379: =DATEDIF(Table1[[#This Row],[EMI_payment_date]],TODAY(),"m") -> 14 | O379: =15*Table1[[#This Row],[monthly_EMI]] -> 598500 | P379: 7.07 | Q379: =Table1[[#This Row],[monthly_income]]*30% -> 39900 | R379: =ROUNDUP(NPER(P379/100/12,-Q379,Table1[[#This Row],[Loan_Amount]]),0) -> 53 | S379: 704 | T379: Late | U379: =IF(Table1[[#This Row],[Repayment_Status]]="late","bad loan","good loan") -> bad loan | V379: =IF(Table1[[#This Row],[Repayment_Status]]="late","high","low") -> high | W379: =(Table1[[#This Row],[monthly_EMI]]/Table1[[#This Row],[monthly_income]])*100 -> 30 | X379: 20284.75
... A397: L0029 | B397: Karan Kumar | C397: 23 | D397: Female | E397: Hyderabad | F397: Business | G397: =YEAR(Table1[[#This Row],[Application_Date]]) -> 2025 | H397: =TEXT(Table1[[#This Row],[EMI_payment_date]],"mmmm") -> May | I397: 45777 | J397: =EDATE(Table1[[#This Row],[Application_Date]],1) -> 45807 | K397: 936000 | L397: =Table1[[#This Row],[Annual_Income]]/12 -> 78000 | M397: 1136000 | N397: =DATEDIF(Table1[[#This Row],[EMI_payment_date]],TODAY(),"m") -> 14 | O397: =15*Table1[[#This Row],[monthly_EMI]] -> 351000 | P397: 5.52 | Q397: =Table1[[#This Row],[monthly_income]]*30% -> 23400 | R397: =ROUNDUP(NPER(P397/100/12,-Q397,Table1[[#This Row],[Loan_Amount]]),0) -> 56 | S397: 794 | T397: Completed | U397: =IF(Table1[[#This Row],[Repayment_Status]]="late","bad loan","good loan") -> good loan | V397: =IF(Table1[[#This Row],[Repayment_Status]]="late","high","low") -> low | W397: =(Table1[[#This Row],[monthly_EMI]]/Table1[[#This Row],[monthly_income]])*100 -> 30 | X397: 21108.36
A398: L0177 | B398: Ritika Singh | C398: 59 | D398: Male | E398: Delhi | F398: Car | G398: =YEAR(Table1[[#This Row],[Application_Date]]) -> 2025 | H398: =TEXT(Table1[[#This Row],[EMI_payment_date]],"mmmm") -> June | I398: 45778 | J398: =EDATE(Table1[[#This Row],[Application_Date]],1) -> 45809 | K398: 2712000 | L398: =Table1[[#This Row],[Annual_Income]]/12 -> 226000 | M398: 2912000 | N398: =DATEDIF(Table1[[#This Row],[EMI_payment_date]],TODAY(),"m") -> 13 | O398: =14*Table1[[#This Row],[monthly_EMI]] -> 949200 | P398: 5.94 | Q398: =Table1[[#This Row],[monthly_income]]*30% -> 67800 | R398: =ROUNDUP(NPER(P398/100/12,-Q398,Table1[[#This Row],[Loan_Amount]]),0) -> 49 | S398: 698 | T398: Late | U398: =IF(Table1[[#This Row],[Repayment_Status]]="late","bad loan","good loan") -> bad loan | V398: =IF(Table1[[#This Row],[Repayment_Status]]="late","high","low") -> high | W398: =(Table1[[#This Row],[monthly_EMI]]/Table1[[#This Row],[monthly_income]])*100 -> 30 | X398: 16196.97
A399: L0621 | B399: Karan Joshi | C399: 57 | D399: Female | E399: Bengaluru | F399: Home | G399: =YEAR(Table1[[#This Row],[Application_Date]]) -> 2025 | H399: =TEXT(Table1[[#This Row],[EMI_payment_date]],"mmmm") -> June | I399: 45779 | J399: =EDATE(Table1[[#This Row],[Application_Date]],1) -> 45810 | K399: 8040000 | L399: =Table1[[#This Row],[Annual_Income]]/12 -> 670000 | M399: 8240000 | N399: =DATEDIF(Table1[[#This Row],[EMI_payment_date]],TODAY(),"m") -> 13 | O399: =14*Table1[[#This Row],[monthly_EMI]] -> 2814000 | P399: 6.34 | Q399: =Table1[[#This Row],[monthly_income]]*30% -> 201000 | R399: =ROUNDUP(NPER(P399/100/12,-Q399,Table1[[#This Row],[Loan_Amount]]),0) -> 47 | S399: 637 | T399: Late | U399: =IF(Table1[[#This Row],[Repayment_Status]]="late","bad loan","good loan") -> bad loan | V399: =IF(Table1[[#This Row],[Repayment_Status]]="late","high","low") -> high | W399: =(Table1[[#This Row],[monthly_EMI]]/Table1[[#This Row],[monthly_income]])*100 -> 30 | X399: 23673.59
A400: L0363 | B400: Sanya Joshi | C400: 32 | D400: Female | E400: Chennai | F400: Education | G400: =YEAR(Table1[[#This Row],[Application_Date]]) -> 2025 | H400: =TEXT(Table1[[#This Row],[EMI_payment_date]],"mmmm") -> June | I400: 45780 | J400: =EDATE(Table1[[#This Row],[Application_Date]],1) -> 45811 | K400: 4944000 | L400: =Table1[[#This Row],[Annual_Income]]/12 -> 412000 | M400: 5144000 | N400: =DATEDIF(Table1[[#This Row],[EMI_payment_date]],TODAY(),"m") -> 13 | O400: =14*Table1[[#This Row],[monthly_EMI]] -> 1730400 | P400: 6.37 | Q400: =Table1[[#This Row],[monthly_income]]*30% -> 123600 | R400: =ROUNDUP(NPER(P400/100/12,-Q400,Table1[[#This Row],[Loan_Amount]]),0) -> 48 | S400: 741 | T400: Late | U400: =IF(Table1[[#This Row],[Repayment_Status]]="late","bad loan","good loan") -> bad loan | V400: =IF(Table1[[#This Row],[Repayment_Status]]="late","high","low") -> high | W400: =(Table1[[#This Row],[monthly_EMI]]/Table1[[#This Row],[monthly_income]])*100 -> 30 | X400: 8252.18
...

Sheet pivot table
A2: total metrics | D2: gender wise customer and loan amount | H2: Repayment Status wise customers | K2: city wise analysis | N2: Average Income by City
A3: metrics | D3: Row Labels | E3: Sum of Loan_Amount | F3: Count of Loan_ID | H3: Row Labels | I3: Count of Loan_ID | K3: Row Labels | L3: Count of Loan_ID | N3: Row Labels | O3: Average of Annual_Income
A4: Count of Loan_ID | B4: 699 | D4: Female | E4: 1709408000 | F4: 337 | H4: Completed | I4: 457 | K4: Bengaluru | L4: 119 | N4: Bengaluru | O4: 4881075.6
A5: Sum of Loan_Amount | B5: 3494112000 | D5: Male | E5: 1784704000 | F5: 362 | H5: Late | I5: 242 | K5: Chennai | L5: 107 | N5: Chennai | O5: 4964972
A6: Average of Interest_Rate | B6: 7.5090844 | K6: Delhi | L6: 136 | N6: Delhi | O6: 4823735.3
A7: Average of total_amount_paid | B7: 1930221.6 | D7: City Wise Good vs Bad Loan analysis | K7: Hyderabad | L7: 110 | N7: Hyderabad | O7: 4779709.1
A8: Average of DTI | B8: 30 | D8: Count of Loan_ID | E8: Column Labels | H8: Default Risk Distribution | K8: Mumbai | L8: 116 | N8: Mumbai | O8: 4543344.8
A9: Sum of Profit | B9: 14829045 | D9: Row Labels | E9: bad loan | F9: good loan | H9: Row Labels | I9: Count of Loan_ID | K9: Pune | L9: 111 | N9: Pune | O9: 4805297.3
D10: Bengaluru | E10: 38 | F10: 81 | H10: high | I10: 242
A11: loan tpye wise analysis | D11: Chennai | E11: 37 | F11: 70 | H11: low | I11: 457 | K11: Average Interest Rate by Loan Type | N11: loan taken by city
A12: Row Labels | B12: Sum of Loan_Amount | D12: Delhi | E12: 58 | F12: 78 | K12: Row Labels | L12: Average of Interest_Rate | N12: Row Labels | O12: Sum of Loan_Amount
A13: Business | B13: 675944000 | D13: Hyderabad | E13: 38 | F13: 72 | K13: Business | L13: 7.6013971 | N13: Bengaluru | O13: 604648000
A14: Car | B14: 661352000 | D14: Mumbai | E14: 34 | F14: 82 | H14: Total Profit by Loan Type | K14: Car | L14: 7.5224194 | N14: Chennai | O14: 552652000
A15: Education | B15: 739476000 | D15: Pune | E15: 37 | F15: 74 | H15: Row Labels | I15: Sum of Profit | K15: Education | L15: 7.5765359 | N15: Delhi | O15: 683228000
A16: Home | B16: 706604000 | H16: Business | I16: 2862769.3 | K16: Home | L16: 7.4301408 | N16: Hyderabad | O16: 547768000
A17: Personal | B17: 710736000 | D17: Total Amount Paid by Loan Type | H17: Car | I17: 2799302.7 | K17: Personal | L17: 7.4165972 | N17: Mumbai | O17: 550228000
D18: Row Labels | E18: Sum of total_amount_paid | H18: Education | I18: 3151641.1 | N18: Pune | O18: 555588000
A19: City Wise Profit | D19: Business | E19: 268450500 | H19: Home | I19: 3135051.7
A20: Row Labels | B20: Sum of Profit | D20: Car | E20: 255999300 | H20: Personal | I20: 2880280 | K20: Total EMI Collected
A21: Bengaluru | B21: 2477866.4 | D21: Education | E21: 258431100 | K21: Row Labels | L21: Sum of monthly_EMI
A22: Chennai | B22: 2123362.9 | D22: Home | E22: 280035600 | K22: Business | L22: 16218600
A23: Delhi | B23: 3050533.5 | D23: Personal | E23: 278587500 | K23: Car | L23: 15913800
A24: Hyderabad | B24: 2207168.3 | K24: Education | L24: 17721900
A25: Mumbai | B25: 2573551 | K25: Home | L25: 16955100
A26: Pune | B26: 2396562.7 | K26: Personal | L26: 17048400

Sheet deshboard
A8: total loan ID | G8: total loan amount | M8: average loan interest rate | S8: total amount recevied | X8: profit
A10: =GETPIVOTDATA("Count of Loan_ID",'pivot table'!$A$3) -> 699 | G10: =GETPIVOTDATA("Sum of Loan_Amount",'pivot table'!$A$3) -> 3494112000 | M10: =GETPIVOTDATA("Average of Interest_Rate",'pivot table'!$A$3) -> 7.5090844 | S10: =GETPIVOTDATA("Average of total_amount_paid",'pivot table'!$A$3) -> 1930221.6 | X10: =GETPIVOTDATA("Sum of Profit",'pivot table'!$A$3) -> 14829045

Sheet insights

Sheet formula used 
A1: formula used | B1: explanation
A2: =_xlfn.FORMULATEXT(data!J3) -> =EDATE([@[Application_Date]],1) | B2: Calculates the first EMI payment date by adding one month to the application date.
A3: =_xlfn.FORMULATEXT(Table1[[#This Row],[years]]) -> =YEAR([@[Application_Date]]) | B3: Calculates and extracts the year from the Application Date for year-wise analysis and reporting.
A4: =_xlfn.FORMULATEXT(Table1[[#This Row],[months]]) -> =TEXT([@[EMI_payment_date]],"mmmm") | B4: Extracts the full month name from the EMI payment date.
A5: =_xlfn.FORMULATEXT(data!L3) -> =[@[Annual_Income]]/12 | B5: Calculates the customer's monthly income from the annual income.
A6: =_xlfn.FORMULATEXT(data!Q3) -> =[@[monthly_income]]*30% | B6: Calculates 30% of the customer's monthly income to estimate the affordable EMI amount.
A7: =_xlfn.FORMULATEXT(data!O3) -> =[@[month_paid]]*[@[monthly_EMI]] | B7: Calculates the total amount paid by multiplying the number of EMIs paid by the monthly EMI amount.
A8: =_xlfn.FORMULATEXT(data!N3) -> =DATEDIF([@[EMI_payment_date]],TODAY(),"m") | B8: Calculates the total number of months elapsed since the EMI payment started.
A9: =_xlfn.FORMULATEXT(data!R3) -> =ROUNDUP(NPER(P3/100/12,-Q3,[@[Loan_Amount]]),0) | B9: Calculates the total loan repayment period (in months) and rounds it up to the nearest whole month.
A10: =_xlfn.FORMULATEXT(data!U3) -> =IF([@[Repayment_Status]]="late","bad loan","good loan") | B10: Classifies the loan as Good Loan or Bad Loan based on the repayment status.
A11: =_xlfn.FORMULATEXT(data!V3) -> =IF([@[Repayment_Status]]="late","high","low") | B11: Determines the default risk level as High or Low based on the repayment status.
A12: =_xlfn.FORMULATEXT(data!W3) -> =([@[monthly_EMI]]/[@[monthly_income]])*100 | B12: Calculates the Debt-to-Income (DTI) ratio by expressing the monthly EMI as a percentage of the monthly income.
